{
  "ComponentIndexes": {
    "Navigation": 11
  },
  "ControlUniqueGuids": {},
  "ControlUniqueIds": {
    "AboutDescription": 263,
    "AboutLeaveGallerySeparator": 274,
    "AboutLeaveMiddle": 277,
    "AboutLeaveTypeButton": 271,
    "AboutLeaveTypeDescription": 275,
    "AboutLeaveTypeGallery": 268,
    "AboutLeaveTypeIcon": 273,
    "AboutLeaveTypeLabel": 272,
    "AboutLeveTypeCell": 270,
    "AboutScreen": 255,
    "AboutTitle": 267,
    "App": 1,
    "Body1": 81,
    "BtnEmailRequester": 99,
    "BtnEmployeeLogin": 250,
    "BtnManagerApprove": 97,
    "BtnManagerDecline": 98,
    "BtnManagerLogin": 251,
    "Button1": 40,
    "Button2": 213,
    "Button3": 214,
    "Button3_1": 223,
    "Button3_2": 216,
    "Button4": 215,
    "Button5": 80,
    "Button6": 141,
    "ButtonCategories": 56,
    "ButtonFilter": 54,
    "CDVBHeader": 155,
    "CDVBHeader_1": 17,
    "CDVBHeaderBackground": 147,
    "CDVBHeaderBackground_1": 153,
    "CDVBHeaderBackground_2": 10,
    "CDVBHeaderSubTitle": 150,
    "CDVBHeaderSubTitle_1": 13,
    "CDVBHeaderTitle": 149,
    "CDVBHeaderTitle_1": 12,
    "CDVBHeaderTitle1": 148,
    "CDVBHeaderTitle1_1": 11,
    "Circle1": 93,
    "CircleHeaderCreateNew_1": 24,
    "CircleHeaderCreateNew_2": 261,
    "CircleHeaderCreateNew_3": 162,
    "CircleHeaderCreateNew_5": 232,
    "CircleHeaderCreateNew_6": 110,
    "CircleHeaderCreateNew_7": 190,
    "CircleHeaderCreateNew_9": 51,
    "CollectionContent": 15,
    "Collections and Variables": 9,
    "CompanyHolidaysScreen": 18,
    "DataCardKey1": 62,
    "DataCardKey2": 65,
    "DataCardKey3": 68,
    "DataCardKey4": 71,
    "DataCardValue_Days": 69,
    "DataCardValue_DecisonBy": 72,
    "DataCardValue_LeaveType": 66,
    "DataCardValue_RequestedTo": 63,
    "DatePicker1": 173,
    "Days_DataCard3": 67,
    "Decision_By_DataCard4": 70,
    "EditIcon": 47,
    "EditLable": 44,
    "Gallery2": 5,
    "Gallery6": 197,
    "GalleryHolidays": 31,
    "GalleryNavigation_12": 112,
    "GalleryRequest": 73,
    "GalleryRequestDetails": 88,
    "galleryTemplate1": 55,
    "galleryTemplate10": 74,
    "galleryTemplate11": 198,
    "galleryTemplate2": 238,
    "galleryTemplate2_14": 113,
    "galleryTemplate2_8": 120,
    "galleryTemplate2_9": 269,
    "galleryTemplate4": 89,
    "galleryTemplate5": 6,
    "galleryTemplate6": 32,
    "galleryTemplate8_1": 180,
    "Group1": 42,
    "Group2": 181,
    "Group3": 182,
    "GroupDateSection": 143,
    "GroupEmptyState": 101,
    "GroupLeaveType": 145,
    "GroupRequestDetails": 102,
    "GroupRequestInfo": 144,
    "GroupRequestInfo_1": 225,
    "Header_1": 142,
    "Header_11": 100,
    "Header_2": 41,
    "Header_3": 276,
    "Header_4": 183,
    "Header_6": 244,
    "Header_9": 211,
    "HeaderBackgroundImage": 246,
    "HolidayDate": 39,
    "HomeScreen": 43,
    "Host": 3,
    "HtmlText1": 152,
    "HtmlText2": 154,
    "Icon1": 196,
    "Icon2": 171,
    "icon2_1": 109,
    "Icon2_1": 172,
    "icon2_11": 50,
    "icon2_2": 23,
    "icon2_3": 260,
    "icon2_4": 161,
    "icon2_6": 231,
    "icon2_9": 189,
    "Icon3": 35,
    "icon5_10": 14,
    "icon5_9": 151,
    "icon7": 94,
    "IconHeaderCreateNew_1": 25,
    "IconHeaderCreateNew_2": 262,
    "IconHeaderCreateNew_3": 163,
    "IconHeaderCreateNew_5": 233,
    "IconHeaderCreateNew_6": 111,
    "IconHeaderCreateNew_7": 191,
    "IconHeaderCreateNew_9": 52,
    "IconRequesterEdit": 95,
    "Image1_1": 92,
    "Image2_1": 220,
    "IMPORTANT_NOTE_READ_ME": 146,
    "Label1": 76,
    "Label1_1": 126,
    "Label1_11": 129,
    "Label1_12": 130,
    "Label1_13": 125,
    "Label1_14": 219,
    "Label1_15": 222,
    "Label1_16": 221,
    "Label1_2": 128,
    "Label1_3": 127,
    "Label1_4": 136,
    "Label1_5": 137,
    "Label1_6": 218,
    "Label1_7": 138,
    "Label1_8": 133,
    "Label1_9": 134,
    "Label10": 201,
    "Label11": 90,
    "Label12": 33,
    "Label13": 34,
    "Label14": 207,
    "Label15": 166,
    "Label16": 176,
    "Label16_1": 177,
    "Label17": 178,
    "Label18": 208,
    "Label19": 179,
    "Label2": 7,
    "Label2_12": 114,
    "Label20": 193,
    "Label22": 204,
    "Label23": 202,
    "Label24": 203,
    "Label26": 205,
    "Label3": 77,
    "Label4": 30,
    "Label5": 139,
    "Label6": 174,
    "Label6_1": 175,
    "Label7": 37,
    "Label8": 107,
    "Label9": 200,
    "Label9_3": 91,
    "LblEmployeeLogin": 248,
    "LblEmptyRequests": 85,
    "LblFirstRequest": 86,
    "LblHeaderCreateNew_1": 22,
    "LblHeaderCreateNew_2": 259,
    "LblHeaderCreateNew_3": 160,
    "LblHeaderCreateNew_5": 230,
    "LblHeaderCreateNew_6": 108,
    "LblHeaderCreateNew_7": 188,
    "LblHeaderCreateNew_9": 49,
    "LblHeaderTItle1_1": 105,
    "LblHeaderTItle1_11": 46,
    "LblHeaderTItle1_2": 20,
    "LblHeaderTItle1_3": 257,
    "LblHeaderTItle1_4": 158,
    "LblHeaderTItle1_6": 228,
    "LblHeaderTItle1_9": 186,
    "LblHeaderTitle2_1": 106,
    "LblHeaderTitle2_11": 48,
    "LblHeaderTitle2_2": 21,
    "LblHeaderTitle2_3": 258,
    "LblHeaderTitle2_4": 159,
    "LblHeaderTitle2_6": 229,
    "LblHeaderTitle2_9": 187,
    "LblHolidaysHeader": 29,
    "LblManagerLogin": 249,
    "LblRequestDetailsHeader": 87,
    "LblRequesterEdit": 96,
    "Leave_Type_DataCard2": 64,
    "LeaveBalance": 168,
    "LeaveBalanceScreen": 156,
    "LeaveEndDatePicker": 132,
    "LeaveInformationScreen": 184,
    "LeaveStartDatePicker": 131,
    "LeftMenuSeparator_12": 115,
    "LoginAsEmployeeGroup": 253,
    "LoginAsManagerGroup": 254,
    "LoginScreen": 245,
    "Navigation": 4,
    "Navigation_1": 234,
    "Navigation_2": 192,
    "Navigation_3": 265,
    "Navigation_4": 27,
    "Navigation_5": 57,
    "Navigation_6": 164,
    "Navigation_7": 116,
    "NewRequestLeaveTypeGallery": 119,
    "NewRequestScreen": 103,
    "NewRequestSeparator": 124,
    "NoData": 84,
    "NRLeaveCellBK": 121,
    "NRLeaveTypeButton": 122,
    "NRLeaveTypeLabel": 123,
    "Rectangle1": 243,
    "Rectangle1_1": 104,
    "Rectangle1_11": 45,
    "Rectangle1_2": 19,
    "Rectangle1_3": 256,
    "Rectangle1_4": 157,
    "Rectangle1_6": 227,
    "Rectangle1_9": 185,
    "Rectangle13": 8,
    "Rectangle17": 199,
    "Rectangle18": 206,
    "Rectangle2": 75,
    "Rectangle2_1": 83,
    "Rectangle20": 209,
    "Rectangle20_1": 194,
    "Rectangle3": 53,
    "Rectangle3_2": 26,
    "Rectangle3_3": 264,
    "Rectangle4": 117,
    "Rectangle5": 36,
    "Rectangle6": 167,
    "Rectangle7": 169,
    "Rectangle7_1": 170,
    "Rectangle9": 242,
    "RectNavSep": 58,
    "RectNavSep_1": 28,
    "RectNavSep_2": 266,
    "RectNavSep_3": 165,
    "RectNavSep_5": 235,
    "RectSeparator_1": 135,
    "RectSeparator_2": 217,
    "RequestDetail": 60,
    "RequestDetailsTitle": 59,
    "Requested_to_DataCard1": 61,
    "RequestLabel": 247,
    "Screen1": 212,
    "SearchInput": 195,
    "Separator1": 82,
    "Separator7": 210,
    "Subtitle1": 79,
    "TextInput1_1": 140,
    "TextInput1_2": 224,
    "Title1": 78,
    "TodayOnLeaveDuration": 241,
    "TodayOnLeaveGallery": 237,
    "TodayOnLeaveName": 239,
    "TodayOnLeaveScreen": 226,
    "TodayOnLeaveTitle": 236,
    "TodayOnLeaveType": 240,
    "txtHoliday": 38,
    "TypeRequestTitle": 118,
    "VariablesContent": 16,
    "WelcomePageHeaderGroup": 252
  },
  "FunctionParamsInvariantScripts": {},
  "FunctionParamsInvariantScriptsOnInstances": {},
  "HeaderLastSavedDateTimeUTC": "11/23/2023 06:00:48",
  "IsLegacyComponentAllowGlobalScopeCase": false,
  "LocalConnectionIDReferences": {
    "12f73af9-777f-4fd4-a512-da2f66fd7501": "\"/providers/microsoft.powerapps/apis/shared_office365/connections/eefb4da557ef4127b9b1aea660ab9aea\"",
    "6f72918a-7921-fa64-14bf-78187ad1b172": "\"/providers/microsoft.powerapps/apis/shared_office365users/connections/689118eeafba44f09861de59a156bfbf\"",
    "81d384ae-de03-4521-b437-163eeda7a732": "\"/providers/microsoft.powerapps/apis/shared_teams/connections/shared-teams-a28f5745-3922-4224-9276-290e7e4dfd5a\"",
    "bdef884f-b8ab-424c-8509-321850292346": "\"/providers/microsoft.powerapps/apis/shared_sharepointonline/connections/98f6e33d3e56454fb95241c212fe0edc\""
  },
  "LocalDatabaseReferencesAsEmpty": false,
  "LocalResourceFileNames": {
    "Basel_Clock": "0001.svg",
    "Basel_detail_list": "0002.svg",
    "bereavement": "0004.png",
    "bereavement-selected": "0003.png",
    "floating-holiday": "0006.png",
    "floating-holiday-selected": "0005.png",
    "Info": "0007.png",
    "jury-duty": "0009.png",
    "jury-duty-selected": "0008.png",
    "login-pic": "0010.png",
    "RequestLeaveBkg": "0011.png",
    "sick-leave": "0013.png",
    "sick-leave-selected": "0012.png",
    "vacation": "0015.png",
    "vacation-selected": "0014.png"
  },
  "LocalResourceRootPaths": {
    "Basel_Clock": "https://docserverpwaprodseas.blob.core.windows.net/0dbf294a-79f1-4801-a336-44c4d21a9ec1-1/resource/Assets0Images00001.svg?skoid=58690ece-ec83-4ce2-9ce8-883d4d6a54ee&sktid=975f013f-7f24-47e8-a7d3-abc4752bf346&skt=2023-11-23T05%3A44%3A44Z&ske=2023-11-24T05%3A59%3A44Z&sks=b&skv=2021-12-02&sv=2021-12-02&spr=https&se=2023-11-24T05%3A59%3A44Z&sr=b&sp=r&sig=ORHILrd%2BOP%2Fgt5EJlAgW2w1Q7TPVb09tJFTCwYzcNmk%3D",
    "Basel_detail_list": "https://docserverpwaprodseas.blob.core.windows.net/0dbf294a-79f1-4801-a336-44c4d21a9ec1-1/resource/Assets0Images00002.svg?skoid=58690ece-ec83-4ce2-9ce8-883d4d6a54ee&sktid=975f013f-7f24-47e8-a7d3-abc4752bf346&skt=2023-11-23T05%3A44%3A44Z&ske=2023-11-24T05%3A59%3A44Z&sks=b&skv=2021-12-02&sv=2021-12-02&spr=https&se=2023-11-24T05%3A59%3A44Z&sr=b&sp=r&sig=8SJ1EEy9hDNeE7SC14YyQYjp3c1eDxwysrVb906daKw%3D",
    "bereavement": "https://docserverpwaprodseas.blob.core.windows.net/0dbf294a-79f1-4801-a336-44c4d21a9ec1-1/resource/Assets0Images00004.png?skoid=58690ece-ec83-4ce2-9ce8-883d4d6a54ee&sktid=975f013f-7f24-47e8-a7d3-abc4752bf346&skt=2023-11-23T05%3A44%3A44Z&ske=2023-11-24T05%3A59%3A44Z&sks=b&skv=2021-12-02&sv=2021-12-02&spr=https&se=2023-11-24T05%3A59%3A44Z&sr=b&sp=r&sig=RnAIPjcVqHIQryKaQa8lNffoKkgXJPFNqsSOjQWSUpU%3D",
    "bereavement-selected": "https://docserverpwaprodseas.blob.core.windows.net/0dbf294a-79f1-4801-a336-44c4d21a9ec1-1/resource/Assets0Images00003.png?skoid=58690ece-ec83-4ce2-9ce8-883d4d6a54ee&sktid=975f013f-7f24-47e8-a7d3-abc4752bf346&skt=2023-11-23T05%3A44%3A44Z&ske=2023-11-24T05%3A59%3A44Z&sks=b&skv=2021-12-02&sv=2021-12-02&spr=https&se=2023-11-24T05%3A59%3A44Z&sr=b&sp=r&sig=UGxrmbAEUzjhQXOMDm2eyHll876Xg2otgSRoBVKzqL8%3D",
    "floating-holiday": "https://docserverpwaprodseas.blob.core.windows.net/0dbf294a-79f1-4801-a336-44c4d21a9ec1-1/resource/Assets0Images00006.png?skoid=58690ece-ec83-4ce2-9ce8-883d4d6a54ee&sktid=975f013f-7f24-47e8-a7d3-abc4752bf346&skt=2023-11-23T05%3A44%3A45Z&ske=2023-11-24T05%3A59%3A45Z&sks=b&skv=2021-12-02&sv=2021-12-02&spr=https&se=2023-11-24T05%3A59%3A45Z&sr=b&sp=r&sig=GKxfO1dWIdWqKSquuCknHYS2hTRwPDzsYX%2F%2BvVjZ3HE%3D",
    "floating-holiday-selected": "https://docserverpwaprodseas.blob.core.windows.net/0dbf294a-79f1-4801-a336-44c4d21a9ec1-1/resource/Assets0Images00005.png?skoid=58690ece-ec83-4ce2-9ce8-883d4d6a54ee&sktid=975f013f-7f24-47e8-a7d3-abc4752bf346&skt=2023-11-23T05%3A44%3A44Z&ske=2023-11-24T05%3A59%3A44Z&sks=b&skv=2021-12-02&sv=2021-12-02&spr=https&se=2023-11-24T05%3A59%3A44Z&sr=b&sp=r&sig=iKVylaNodWS8RFqMHUXHk%2Fqa1yOWufToT%2BocYXMBovc%3D",
    "Info": "https://docserverpwaprodseas.blob.core.windows.net/0dbf294a-79f1-4801-a336-44c4d21a9ec1-1/resource/Assets0Images00007.png?skoid=58690ece-ec83-4ce2-9ce8-883d4d6a54ee&sktid=975f013f-7f24-47e8-a7d3-abc4752bf346&skt=2023-11-23T05%3A44%3A45Z&ske=2023-11-24T05%3A59%3A45Z&sks=b&skv=2021-12-02&sv=2021-12-02&spr=https&se=2023-11-24T05%3A59%3A45Z&sr=b&sp=r&sig=EoLjLG8LtvPIkiuk9SzNCMVIt71Iv4w8c8qsQBzN4is%3D",
    "jury-duty": "https://docserverpwaprodseas.blob.core.windows.net/0dbf294a-79f1-4801-a336-44c4d21a9ec1-1/resource/Assets0Images00009.png?skoid=58690ece-ec83-4ce2-9ce8-883d4d6a54ee&sktid=975f013f-7f24-47e8-a7d3-abc4752bf346&skt=2023-11-23T05%3A44%3A45Z&ske=2023-11-24T05%3A59%3A45Z&sks=b&skv=2021-12-02&sv=2021-12-02&spr=https&se=2023-11-24T05%3A59%3A45Z&sr=b&sp=r&sig=qf6s3U7pfoxYgN%2B6rq5lRBAnYrs9r0UThabquAFR9uU%3D",
    "jury-duty-selected": "https://docserverpwaprodseas.blob.core.windows.net/0dbf294a-79f1-4801-a336-44c4d21a9ec1-1/resource/Assets0Images00008.png?skoid=58690ece-ec83-4ce2-9ce8-883d4d6a54ee&sktid=975f013f-7f24-47e8-a7d3-abc4752bf346&skt=2023-11-23T05%3A44%3A45Z&ske=2023-11-24T05%3A59%3A45Z&sks=b&skv=2021-12-02&sv=2021-12-02&spr=https&se=2023-11-24T05%3A59%3A45Z&sr=b&sp=r&sig=qUvW0hiTUINYJGzCpaIdiA97m0DHwEfl6U%2BJ8FsE9J8%3D",
    "login-pic": "https://docserverpwaprodseas.blob.core.windows.net/0dbf294a-79f1-4801-a336-44c4d21a9ec1-1/resource/Assets0Images00010.png?skoid=58690ece-ec83-4ce2-9ce8-883d4d6a54ee&sktid=975f013f-7f24-47e8-a7d3-abc4752bf346&skt=2023-11-23T05%3A44%3A45Z&ske=2023-11-24T05%3A59%3A45Z&sks=b&skv=2021-12-02&sv=2021-12-02&spr=https&se=2023-11-24T05%3A59%3A45Z&sr=b&sp=r&sig=SypZosc2AYXAdnJkMIETNrEXU0UkeWzmfKry8ixYbbo%3D",
    "RequestLeaveBkg": "https://docserverpwaprodseas.blob.core.windows.net/0dbf294a-79f1-4801-a336-44c4d21a9ec1-1/resource/Assets0Images00011.png?skoid=58690ece-ec83-4ce2-9ce8-883d4d6a54ee&sktid=975f013f-7f24-47e8-a7d3-abc4752bf346&skt=2023-11-23T05%3A44%3A45Z&ske=2023-11-24T05%3A59%3A45Z&sks=b&skv=2021-12-02&sv=2021-12-02&spr=https&se=2023-11-24T05%3A59%3A45Z&sr=b&sp=r&sig=MLJ5yw1lyO3r4BGXG2N2JYl7md0%2B6czO%2BhmryV7fkLQ%3D",
    "sick-leave": "https://docserverpwaprodseas.blob.core.windows.net/0dbf294a-79f1-4801-a336-44c4d21a9ec1-1/resource/Assets0Images00013.png?skoid=58690ece-ec83-4ce2-9ce8-883d4d6a54ee&sktid=975f013f-7f24-47e8-a7d3-abc4752bf346&skt=2023-11-23T05%3A44%3A45Z&ske=2023-11-24T05%3A59%3A45Z&sks=b&skv=2021-12-02&sv=2021-12-02&spr=https&se=2023-11-24T05%3A59%3A45Z&sr=b&sp=r&sig=KcXh4OPL3eiC1zefeRVux1b90M9%2BJu5uPe4ByynlTUg%3D",
    "sick-leave-selected": "https://docserverpwaprodseas.blob.core.windows.net/0dbf294a-79f1-4801-a336-44c4d21a9ec1-1/resource/Assets0Images00012.png?skoid=58690ece-ec83-4ce2-9ce8-883d4d6a54ee&sktid=975f013f-7f24-47e8-a7d3-abc4752bf346&skt=2023-11-23T05%3A44%3A45Z&ske=2023-11-24T05%3A59%3A45Z&sks=b&skv=2021-12-02&sv=2021-12-02&spr=https&se=2023-11-24T05%3A59%3A45Z&sr=b&sp=r&sig=lxbI75cjOEW4FH9mSuGKjr4A6fA%2Fv5bTZb%2B5f2AQdug%3D",
    "vacation": "https://docserverpwaprodseas.blob.core.windows.net/0dbf294a-79f1-4801-a336-44c4d21a9ec1-1/resource/Assets0Images00015.png?skoid=58690ece-ec83-4ce2-9ce8-883d4d6a54ee&sktid=975f013f-7f24-47e8-a7d3-abc4752bf346&skt=2023-11-23T05%3A44%3A45Z&ske=2023-11-24T05%3A59%3A45Z&sks=b&skv=2021-12-02&sv=2021-12-02&spr=https&se=2023-11-24T05%3A59%3A45Z&sr=b&sp=r&sig=i5i2fTCt9hjmQ1nL4YiY9InBDQWyY2vhQH5j3zFoMnw%3D",
    "vacation-selected": "https://docserverpwaprodseas.blob.core.windows.net/0dbf294a-79f1-4801-a336-44c4d21a9ec1-1/resource/Assets0Images00014.png?skoid=58690ece-ec83-4ce2-9ce8-883d4d6a54ee&sktid=975f013f-7f24-47e8-a7d3-abc4752bf346&skt=2023-11-23T05%3A44%3A45Z&ske=2023-11-24T05%3A59%3A45Z&sks=b&skv=2021-12-02&sv=2021-12-02&spr=https&se=2023-11-24T05%3A59%3A45Z&sr=b&sp=r&sig=jLUWzQewJYpLMw5MdsSASiVl%2FdV%2BFv59zs8DbeZnsn0%3D"
  },
  "OldLogoFileName": "logo.jpg",
  "OrderComponentMetadata": {
    "b6b5e691fc474668b7b6312386d8a5c2": 0
  },
  "OrderComponentTemplate": {
    "b6b5e691fc474668b7b6312386d8a5c2": 0
  },
  "OrderDataSource": {
    "ComboBoxSample": 4,
    "CustomGallerySample": 5,
    "DropDownSample": 6,
    "EmailTemplate": 28,
    "EmployeeNavigation": 29,
    "HolidaysCollection": 30,
    "LeaveApp_Employee": 7,
    "LeaveApp_Request": 8,
    "LeaveTypeCollection": 31,
    "ListboxSample": 9,
    "ManagerNavigation": 32,
    "MicrosoftTeams": 0,
    "Office365": 1,
    "Office365Users": 2,
    "Office365Users_1": 3,
    "RequesterBalanceCollection": 33,
    "Table1": 10,
    "Table1_1": 11,
    "Table1_10": 12,
    "Table1_11": 13,
    "Table1_12": 14,
    "Table1_13": 15,
    "Table1_14": 16,
    "Table1_15": 17,
    "Table1_16": 18,
    "Table1_17": 19,
    "Table1_2": 20,
    "Table1_3": 21,
    "Table1_4": 22,
    "Table1_5": 23,
    "Table1_6": 24,
    "Table1_7": 25,
    "Table1_8": 26,
    "Table1_9": 27
  },
  "OrderGroupControls": {
    "AboutLeaveMiddle": {
      "AboutDescription": 2,
      "AboutLeaveGallerySeparator": 4,
      "AboutLeaveTypeDescription": 3,
      "AboutLeaveTypeGallery": 1,
      "AboutTitle": 0
    },
    "CDVBHeader": {
      "CDVBHeaderBackground": 0,
      "CDVBHeaderSubTitle": 1,
      "CDVBHeaderTitle": 2,
      "CDVBHeaderTitle1": 3
    },
    "CDVBHeader_1": {
      "CDVBHeaderBackground_2": 0,
      "CDVBHeaderSubTitle_1": 1,
      "CDVBHeaderTitle_1": 2,
      "CDVBHeaderTitle1_1": 3
    },
    "Group1": {
      "Button1": 1,
      "Label7": 0
    },
    "Group2": {
      "Icon2": 5,
      "Label16": 2,
      "Label17": 3,
      "Label19": 4,
      "Label6": 1,
      "Rectangle7": 0
    },
    "Group3": {
      "Icon2_1": 3,
      "Label16_1": 2,
      "Label6_1": 1,
      "Rectangle7_1": 0
    },
    "GroupDateSection": {
      "Label1_1": 0,
      "Label1_11": 7,
      "Label1_12": 8,
      "Label1_13": 9,
      "Label1_2": 1,
      "Label1_3": 2,
      "Label1_8": 5,
      "Label1_9": 6,
      "LeaveEndDatePicker": 4,
      "LeaveStartDatePicker": 3
    },
    "GroupEmptyState": {
      "Circle1": 1,
      "icon7": 2,
      "LblEmptyRequests": 3,
      "LblFirstRequest": 0
    },
    "GroupLeaveType": {
      "NewRequestLeaveTypeGallery": 0,
      "NewRequestSeparator": 2,
      "TypeRequestTitle": 1
    },
    "GroupRequestDetails": {
      "BtnEmailRequester": 2,
      "BtnManagerApprove": 4,
      "BtnManagerDecline": 3,
      "GalleryRequestDetails": 1,
      "IconRequesterEdit": 6,
      "LblRequestDetailsHeader": 0,
      "LblRequesterEdit": 5
    },
    "GroupRequestInfo": {
      "Label1_4": 0,
      "Label1_5": 1,
      "Label1_7": 2,
      "RectSeparator_1": 4,
      "TextInput1_1": 3
    },
    "GroupRequestInfo_1": {
      "Button3_1": 7,
      "Image2_1": 4,
      "Label1_14": 1,
      "Label1_15": 2,
      "Label1_16": 5,
      "Label1_6": 0,
      "RectSeparator_2": 6,
      "TextInput1_2": 3
    },
    "Header_1": {
      "CircleHeaderCreateNew_6": 4,
      "icon2_1": 3,
      "IconHeaderCreateNew_6": 5,
      "LblHeaderCreateNew_6": 6,
      "LblHeaderTItle1_1": 1,
      "LblHeaderTitle2_1": 2,
      "Rectangle1_1": 0
    },
    "Header_11": {
      "CircleHeaderCreateNew_9": 4,
      "icon2_11": 3,
      "IconHeaderCreateNew_9": 5,
      "LblHeaderCreateNew_9": 6,
      "LblHeaderTItle1_11": 1,
      "LblHeaderTitle2_11": 2,
      "Rectangle1_11": 0
    },
    "Header_2": {
      "CircleHeaderCreateNew_1": 4,
      "icon2_2": 3,
      "IconHeaderCreateNew_1": 5,
      "LblHeaderCreateNew_1": 6,
      "LblHeaderTItle1_2": 1,
      "LblHeaderTitle2_2": 2,
      "Rectangle1_2": 0
    },
    "Header_3": {
      "CircleHeaderCreateNew_2": 4,
      "icon2_3": 3,
      "IconHeaderCreateNew_2": 5,
      "LblHeaderCreateNew_2": 6,
      "LblHeaderTItle1_3": 1,
      "LblHeaderTitle2_3": 2,
      "Rectangle1_3": 0
    },
    "Header_4": {
      "CircleHeaderCreateNew_3": 4,
      "icon2_4": 3,
      "IconHeaderCreateNew_3": 5,
      "LblHeaderCreateNew_3": 6,
      "LblHeaderTItle1_4": 1,
      "LblHeaderTitle2_4": 2,
      "Rectangle1_4": 0
    },
    "Header_6": {
      "CircleHeaderCreateNew_5": 4,
      "icon2_6": 3,
      "IconHeaderCreateNew_5": 5,
      "LblHeaderCreateNew_5": 6,
      "LblHeaderTItle1_6": 1,
      "LblHeaderTitle2_6": 2,
      "Rectangle1_6": 0
    },
    "Header_9": {
      "CircleHeaderCreateNew_7": 4,
      "icon2_9": 3,
      "IconHeaderCreateNew_7": 5,
      "LblHeaderCreateNew_7": 6,
      "LblHeaderTItle1_9": 1,
      "LblHeaderTitle2_9": 2,
      "Rectangle1_9": 0
    },
    "LoginAsEmployeeGroup": {
      "BtnEmployeeLogin": 1,
      "LblEmployeeLogin": 0
    },
    "LoginAsManagerGroup": {
      "BtnManagerLogin": 1,
      "LblManagerLogin": 0
    },
    "WelcomePageHeaderGroup": {
      "HeaderBackgroundImage": 0,
      "RequestLabel": 1
    }
  },
  "OrderPcfTemplate": {},
  "OrderTemplate": {},
  "OrderXMLTemplate": {
    "button": 8,
    "circle": 4,
    "combobox": 10,
    "datepicker": 7,
    "form": 9,
    "gallery": 5,
    "htmlViewer": 3,
    "icon": 2,
    "image": 11,
    "label": 1,
    "rectangle": 0,
    "text": 6
  },
  "OverridablePropertiesEntry": {
    "AboutDescription": {},
    "AboutLeaveGallerySeparator": {},
    "AboutLeaveMiddle": {},
    "AboutLeaveTypeButton": {},
    "AboutLeaveTypeDescription": {},
    "AboutLeaveTypeGallery": {},
    "AboutLeaveTypeIcon": {},
    "AboutLeaveTypeLabel": {},
    "AboutLeveTypeCell": {},
    "AboutScreen": {},
    "AboutTitle": {},
    "App": {},
    "Body1": {},
    "BtnEmailRequester": {},
    "BtnEmployeeLogin": {},
    "BtnManagerApprove": {},
    "BtnManagerDecline": {},
    "BtnManagerLogin": {},
    "Button1": {},
    "Button2": {},
    "Button3": {},
    "Button3_1": {},
    "Button3_2": {},
    "Button4": {},
    "Button5": {},
    "Button6": {},
    "ButtonCategories": {},
    "ButtonFilter": {},
    "CDVBHeader": {},
    "CDVBHeader_1": {},
    "CDVBHeaderBackground": {},
    "CDVBHeaderBackground_1": {},
    "CDVBHeaderBackground_2": {},
    "CDVBHeaderSubTitle": {},
    "CDVBHeaderSubTitle_1": {},
    "CDVBHeaderTitle": {},
    "CDVBHeaderTitle_1": {},
    "CDVBHeaderTitle1": {},
    "CDVBHeaderTitle1_1": {},
    "Circle1": {},
    "CircleHeaderCreateNew_1": {},
    "CircleHeaderCreateNew_2": {},
    "CircleHeaderCreateNew_3": {},
    "CircleHeaderCreateNew_5": {},
    "CircleHeaderCreateNew_6": {},
    "CircleHeaderCreateNew_7": {},
    "CircleHeaderCreateNew_9": {},
    "CollectionContent": {},
    "Collections and Variables": {},
    "CompanyHolidaysScreen": {},
    "DataCardKey1": {},
    "DataCardKey2": {},
    "DataCardKey3": {},
    "DataCardKey4": {},
    "DataCardValue_Days": {},
    "DataCardValue_DecisonBy": {},
    "DataCardValue_LeaveType": {},
    "DataCardValue_RequestedTo": {},
    "DatePicker1": {},
    "Days_DataCard3": {},
    "Decision_By_DataCard4": {},
    "EditIcon": {},
    "EditLable": {},
    "Gallery2": {},
    "Gallery6": {},
    "GalleryHolidays": {},
    "GalleryNavigation_12": {},
    "GalleryRequest": {},
    "GalleryRequestDetails": {},
    "galleryTemplate1": {},
    "galleryTemplate10": {},
    "galleryTemplate11": {},
    "galleryTemplate2": {},
    "galleryTemplate2_14": {},
    "galleryTemplate2_8": {},
    "galleryTemplate2_9": {},
    "galleryTemplate4": {},
    "galleryTemplate5": {},
    "galleryTemplate6": {},
    "galleryTemplate8_1": {},
    "Group1": {},
    "Group2": {},
    "Group3": {},
    "GroupDateSection": {},
    "GroupEmptyState": {},
    "GroupLeaveType": {},
    "GroupRequestDetails": {},
    "GroupRequestInfo": {},
    "GroupRequestInfo_1": {},
    "Header_1": {},
    "Header_11": {},
    "Header_2": {},
    "Header_3": {},
    "Header_4": {},
    "Header_6": {},
    "Header_9": {},
    "HeaderBackgroundImage": {},
    "HolidayDate": {},
    "HomeScreen": {},
    "Host": {},
    "HtmlText1": {},
    "HtmlText2": {},
    "Icon1": {},
    "Icon2": {},
    "icon2_1": {},
    "Icon2_1": {},
    "icon2_11": {},
    "icon2_2": {},
    "icon2_3": {},
    "icon2_4": {},
    "icon2_6": {},
    "icon2_9": {},
    "Icon3": {},
    "icon5_10": {},
    "icon5_9": {},
    "icon7": {},
    "IconHeaderCreateNew_1": {},
    "IconHeaderCreateNew_2": {},
    "IconHeaderCreateNew_3": {},
    "IconHeaderCreateNew_5": {},
    "IconHeaderCreateNew_6": {},
    "IconHeaderCreateNew_7": {},
    "IconHeaderCreateNew_9": {},
    "IconRequesterEdit": {},
    "Image1_1": {},
    "Image2_1": {},
    "IMPORTANT_NOTE_READ_ME": {},
    "Label1": {},
    "Label1_1": {},
    "Label1_11": {},
    "Label1_12": {},
    "Label1_13": {},
    "Label1_14": {},
    "Label1_15": {},
    "Label1_16": {},
    "Label1_2": {},
    "Label1_3": {},
    "Label1_4": {},
    "Label1_5": {},
    "Label1_6": {},
    "Label1_7": {},
    "Label1_8": {},
    "Label1_9": {},
    "Label10": {},
    "Label11": {},
    "Label12": {},
    "Label13": {},
    "Label14": {},
    "Label15": {},
    "Label16": {},
    "Label16_1": {},
    "Label17": {},
    "Label18": {},
    "Label19": {},
    "Label2": {},
    "Label2_12": {},
    "Label20": {},
    "Label22": {},
    "Label23": {},
    "Label24": {},
    "Label26": {},
    "Label3": {},
    "Label4": {},
    "Label5": {},
    "Label6": {},
    "Label6_1": {},
    "Label7": {},
    "Label8": {},
    "Label9": {},
    "Label9_3": {},
    "LblEmployeeLogin": {},
    "LblEmptyRequests": {},
    "LblFirstRequest": {},
    "LblHeaderCreateNew_1": {},
    "LblHeaderCreateNew_2": {},
    "LblHeaderCreateNew_3": {},
    "LblHeaderCreateNew_5": {},
    "LblHeaderCreateNew_6": {},
    "LblHeaderCreateNew_7": {},
    "LblHeaderCreateNew_9": {},
    "LblHeaderTItle1_1": {},
    "LblHeaderTItle1_11": {},
    "LblHeaderTItle1_2": {},
    "LblHeaderTItle1_3": {},
    "LblHeaderTItle1_4": {},
    "LblHeaderTItle1_6": {},
    "LblHeaderTItle1_9": {},
    "LblHeaderTitle2_1": {},
    "LblHeaderTitle2_11": {},
    "LblHeaderTitle2_2": {},
    "LblHeaderTitle2_3": {},
    "LblHeaderTitle2_4": {},
    "LblHeaderTitle2_6": {},
    "LblHeaderTitle2_9": {},
    "LblHolidaysHeader": {},
    "LblManagerLogin": {},
    "LblRequestDetailsHeader": {},
    "LblRequesterEdit": {},
    "Leave_Type_DataCard2": {},
    "LeaveBalance": {},
    "LeaveBalanceScreen": {},
    "LeaveEndDatePicker": {},
    "LeaveInformationScreen": {},
    "LeaveStartDatePicker": {},
    "LeftMenuSeparator_12": {},
    "LoginAsEmployeeGroup": {},
    "LoginAsManagerGroup": {},
    "LoginScreen": {},
    "Navigation": {},
    "Navigation_1": {},
    "Navigation_2": {},
    "Navigation_3": {},
    "Navigation_4": {},
    "Navigation_5": {},
    "Navigation_6": {},
    "Navigation_7": {},
    "NewRequestLeaveTypeGallery": {},
    "NewRequestScreen": {},
    "NewRequestSeparator": {},
    "NoData": {},
    "NRLeaveCellBK": {},
    "NRLeaveTypeButton": {},
    "NRLeaveTypeLabel": {},
    "Rectangle1": {},
    "Rectangle1_1": {},
    "Rectangle1_11": {},
    "Rectangle1_2": {},
    "Rectangle1_3": {},
    "Rectangle1_4": {},
    "Rectangle1_6": {},
    "Rectangle1_9": {},
    "Rectangle13": {},
    "Rectangle17": {},
    "Rectangle18": {},
    "Rectangle2": {},
    "Rectangle2_1": {},
    "Rectangle20": {},
    "Rectangle20_1": {},
    "Rectangle3": {},
    "Rectangle3_2": {},
    "Rectangle3_3": {},
    "Rectangle4": {},
    "Rectangle5": {},
    "Rectangle6": {},
    "Rectangle7": {},
    "Rectangle7_1": {},
    "Rectangle9": {},
    "RectNavSep": {},
    "RectNavSep_1": {},
    "RectNavSep_2": {},
    "RectNavSep_3": {},
    "RectNavSep_5": {},
    "RectSeparator_1": {},
    "RectSeparator_2": {},
    "RequestDetail": {},
    "RequestDetailsTitle": {},
    "Requested_to_DataCard1": {},
    "RequestLabel": {},
    "Screen1": {},
    "SearchInput": {},
    "Separator1": {},
    "Separator7": {},
    "Subtitle1": {},
    "TextInput1_1": {},
    "TextInput1_2": {},
    "Title1": {},
    "TodayOnLeaveDuration": {},
    "TodayOnLeaveGallery": {},
    "TodayOnLeaveName": {},
    "TodayOnLeaveScreen": {},
    "TodayOnLeaveTitle": {},
    "TodayOnLeaveType": {},
    "txtHoliday": {},
    "TypeRequestTitle": {},
    "VariablesContent": {},
    "WelcomePageHeaderGroup": {}
  },
  "PCFDynamicSchemaForIRRetrievalEntry": {},
  "PCFTemplateEntry": {},
  "PublishOrderIndices": {
    "AboutDescription": 14,
    "AboutLeaveGallerySeparator": 20,
    "AboutLeaveMiddle": 23,
    "AboutLeaveTypeButton": 26,
    "AboutLeaveTypeDescription": 21,
    "AboutLeaveTypeGallery": 19,
    "AboutLeaveTypeIcon": 28,
    "AboutLeaveTypeLabel": 27,
    "AboutLeveTypeCell": 25,
    "AboutScreen": 6,
    "AboutTitle": 18,
    "App": 0,
    "Body1": 119,
    "BtnEmailRequester": 94,
    "BtnEmployeeLogin": 196,
    "BtnManagerApprove": 92,
    "BtnManagerDecline": 93,
    "BtnManagerLogin": 197,
    "Button1": 57,
    "Button2": 245,
    "Button3": 246,
    "Button3_1": 255,
    "Button3_2": 248,
    "Button4": 247,
    "Button5": 118,
    "Button6": 232,
    "ButtonCategories": 99,
    "ButtonFilter": 76,
    "CDVBHeader": 134,
    "CDVBHeader_1": 39,
    "CDVBHeaderBackground": 126,
    "CDVBHeaderBackground_1": 132,
    "CDVBHeaderBackground_2": 32,
    "CDVBHeaderSubTitle": 129,
    "CDVBHeaderSubTitle_1": 35,
    "CDVBHeaderTitle": 128,
    "CDVBHeaderTitle_1": 34,
    "CDVBHeaderTitle1": 127,
    "CDVBHeaderTitle1_1": 33,
    "Circle1": 88,
    "CircleHeaderCreateNew_1": 46,
    "CircleHeaderCreateNew_2": 12,
    "CircleHeaderCreateNew_3": 141,
    "CircleHeaderCreateNew_5": 264,
    "CircleHeaderCreateNew_6": 208,
    "CircleHeaderCreateNew_7": 169,
    "CircleHeaderCreateNew_9": 73,
    "CollectionContent": 37,
    "Collections and Variables": 31,
    "CompanyHolidaysScreen": 40,
    "DataCardKey1": 104,
    "DataCardKey2": 106,
    "DataCardKey3": 108,
    "DataCardKey4": 110,
    "DataCardValue_Days": 109,
    "DataCardValue_DecisonBy": 111,
    "DataCardValue_LeaveType": 107,
    "DataCardValue_RequestedTo": 105,
    "DatePicker1": 153,
    "Days_DataCard3": 102,
    "Decision_By_DataCard4": 103,
    "EditIcon": 69,
    "EditLable": 66,
    "Gallery2": 2,
    "Gallery6": 176,
    "GalleryHolidays": 53,
    "GalleryNavigation_12": 210,
    "GalleryRequest": 81,
    "GalleryRequestDetails": 87,
    "galleryTemplate1": 98,
    "galleryTemplate10": 112,
    "galleryTemplate11": 178,
    "galleryTemplate2": 272,
    "galleryTemplate2_14": 237,
    "galleryTemplate2_8": 240,
    "galleryTemplate2_9": 24,
    "galleryTemplate4": 121,
    "galleryTemplate5": 3,
    "galleryTemplate6": 60,
    "galleryTemplate8_1": 160,
    "Group1": 59,
    "Group2": 161,
    "Group3": 162,
    "GroupDateSection": 234,
    "GroupEmptyState": 96,
    "GroupLeaveType": 236,
    "GroupRequestDetails": 97,
    "GroupRequestInfo": 235,
    "GroupRequestInfo_1": 257,
    "Header_1": 233,
    "Header_11": 95,
    "Header_2": 58,
    "Header_3": 22,
    "Header_4": 148,
    "Header_6": 271,
    "Header_9": 177,
    "HeaderBackgroundImage": 192,
    "HolidayDate": 56,
    "HomeScreen": 65,
    "Host": 0,
    "HtmlText1": 131,
    "HtmlText2": 133,
    "Icon1": 175,
    "Icon2": 151,
    "icon2_1": 207,
    "Icon2_1": 152,
    "icon2_11": 72,
    "icon2_2": 45,
    "icon2_3": 11,
    "icon2_4": 140,
    "icon2_6": 263,
    "icon2_9": 168,
    "Icon3": 63,
    "icon5_10": 36,
    "icon5_9": 130,
    "icon7": 89,
    "IconHeaderCreateNew_1": 47,
    "IconHeaderCreateNew_2": 13,
    "IconHeaderCreateNew_3": 142,
    "IconHeaderCreateNew_5": 265,
    "IconHeaderCreateNew_6": 209,
    "IconHeaderCreateNew_7": 170,
    "IconHeaderCreateNew_9": 74,
    "IconRequesterEdit": 90,
    "Image1_1": 124,
    "Image2_1": 252,
    "IMPORTANT_NOTE_READ_ME": 125,
    "Label1": 114,
    "Label1_1": 217,
    "Label1_11": 220,
    "Label1_12": 221,
    "Label1_13": 216,
    "Label1_14": 251,
    "Label1_15": 254,
    "Label1_16": 253,
    "Label1_2": 219,
    "Label1_3": 218,
    "Label1_4": 227,
    "Label1_5": 228,
    "Label1_6": 250,
    "Label1_7": 229,
    "Label1_8": 224,
    "Label1_9": 225,
    "Label10": 181,
    "Label11": 122,
    "Label12": 61,
    "Label13": 62,
    "Label14": 187,
    "Label15": 145,
    "Label16": 156,
    "Label16_1": 157,
    "Label17": 158,
    "Label18": 188,
    "Label19": 159,
    "Label2": 4,
    "Label2_12": 238,
    "Label20": 172,
    "Label22": 184,
    "Label23": 182,
    "Label24": 183,
    "Label26": 185,
    "Label3": 115,
    "Label4": 52,
    "Label5": 230,
    "Label6": 154,
    "Label6_1": 155,
    "Label7": 54,
    "Label8": 205,
    "Label9": 180,
    "Label9_3": 123,
    "LblEmployeeLogin": 194,
    "LblEmptyRequests": 84,
    "LblFirstRequest": 85,
    "LblHeaderCreateNew_1": 44,
    "LblHeaderCreateNew_2": 10,
    "LblHeaderCreateNew_3": 139,
    "LblHeaderCreateNew_5": 262,
    "LblHeaderCreateNew_6": 206,
    "LblHeaderCreateNew_7": 167,
    "LblHeaderCreateNew_9": 71,
    "LblHeaderTItle1_1": 203,
    "LblHeaderTItle1_11": 68,
    "LblHeaderTItle1_2": 42,
    "LblHeaderTItle1_3": 8,
    "LblHeaderTItle1_4": 137,
    "LblHeaderTItle1_6": 260,
    "LblHeaderTItle1_9": 165,
    "LblHeaderTitle2_1": 204,
    "LblHeaderTitle2_11": 70,
    "LblHeaderTitle2_2": 43,
    "LblHeaderTitle2_3": 9,
    "LblHeaderTitle2_4": 138,
    "LblHeaderTitle2_6": 261,
    "LblHeaderTitle2_9": 166,
    "LblHolidaysHeader": 51,
    "LblManagerLogin": 195,
    "LblRequestDetailsHeader": 86,
    "LblRequesterEdit": 91,
    "Leave_Type_DataCard2": 101,
    "LeaveBalance": 147,
    "LeaveBalanceScreen": 135,
    "LeaveEndDatePicker": 223,
    "LeaveInformationScreen": 163,
    "LeaveStartDatePicker": 222,
    "LeftMenuSeparator_12": 239,
    "LoginAsEmployeeGroup": 199,
    "LoginAsManagerGroup": 200,
    "LoginScreen": 191,
    "Navigation": 1,
    "Navigation_1": 266,
    "Navigation_2": 171,
    "Navigation_3": 16,
    "Navigation_4": 49,
    "Navigation_5": 77,
    "Navigation_6": 143,
    "Navigation_7": 211,
    "NewRequestLeaveTypeGallery": 214,
    "NewRequestScreen": 201,
    "NewRequestSeparator": 215,
    "NoData": 83,
    "NRLeaveCellBK": 241,
    "NRLeaveTypeButton": 242,
    "NRLeaveTypeLabel": 243,
    "Rectangle1": 270,
    "Rectangle1_1": 202,
    "Rectangle1_11": 67,
    "Rectangle1_2": 41,
    "Rectangle1_3": 7,
    "Rectangle1_4": 136,
    "Rectangle1_6": 259,
    "Rectangle1_9": 164,
    "Rectangle13": 5,
    "Rectangle17": 179,
    "Rectangle18": 186,
    "Rectangle2": 113,
    "Rectangle2_1": 82,
    "Rectangle20": 189,
    "Rectangle20_1": 173,
    "Rectangle3": 75,
    "Rectangle3_2": 48,
    "Rectangle3_3": 15,
    "Rectangle4": 212,
    "Rectangle5": 64,
    "Rectangle6": 146,
    "Rectangle7": 149,
    "Rectangle7_1": 150,
    "Rectangle9": 276,
    "RectNavSep": 78,
    "RectNavSep_1": 50,
    "RectNavSep_2": 17,
    "RectNavSep_3": 144,
    "RectNavSep_5": 267,
    "RectSeparator_1": 226,
    "RectSeparator_2": 249,
    "RequestDetail": 80,
    "RequestDetailsTitle": 79,
    "Requested_to_DataCard1": 100,
    "RequestLabel": 193,
    "Screen1": 244,
    "SearchInput": 174,
    "Separator1": 120,
    "Separator7": 190,
    "Subtitle1": 117,
    "TextInput1_1": 231,
    "TextInput1_2": 256,
    "Title1": 116,
    "TodayOnLeaveDuration": 275,
    "TodayOnLeaveGallery": 269,
    "TodayOnLeaveName": 273,
    "TodayOnLeaveScreen": 258,
    "TodayOnLeaveTitle": 268,
    "TodayOnLeaveType": 274,
    "txtHoliday": 55,
    "TypeRequestTitle": 213,
    "VariablesContent": 38,
    "WelcomePageHeaderGroup": 198
  },
  "ResourcesJsonIndices": {
    "Image-Basel_Add": 0,
    "Image-Basel_ArrowRight": 1,
    "Image-Basel_ArrowsUpDown": 2,
    "Image-Basel_Cancel": 3,
    "Image-Basel_Check": 4,
    "Image-Basel_ChevronLeft": 5,
    "Image-Basel_ChevronRight": 6,
    "Image-Basel_Clock": 15,
    "Image-Basel_detail_list": 16,
    "Image-Basel_Edit": 7,
    "Image-Basel_Hamburger": 8,
    "Image-Basel_Information": 9,
    "Image-Basel_Mail": 10,
    "Image-Basel_Person": 11,
    "Image-Basel_Reload": 12,
    "Image-Basel_Search": 13,
    "Image-bereavement": 18,
    "Image-bereavement-selected": 17,
    "Image-floating-holiday": 20,
    "Image-floating-holiday-selected": 19,
    "Image-Info": 21,
    "Image-jury-duty": 23,
    "Image-jury-duty-selected": 22,
    "Image-login-pic": 24,
    "Image-RequestLeaveBkg": 25,
    "Image-SampleImage": 14,
    "Image-sick-leave": 27,
    "Image-sick-leave-selected": 26,
    "Image-vacation": 29,
    "Image-vacation-selected": 28
  },
  "RuleScreenIdWithoutScreen": {},
  "TemplateVersions": {},
  "VolatileProperties": {
    "AnalysisLoadTime": 1.4537717,
    "ControlCount": {
      "b6b5e691fc474668b7b6312386d8a5c2": 8,
      "button": 15,
      "circle": 8,
      "combobox": 3,
      "datepicker": 4,
      "form": 1,
      "gallery": 11,
      "galleryTemplate": 11,
      "group": 22,
      "htmlViewer": 4,
      "icon": 24,
      "image": 4,
      "label": 98,
      "rectangle": 41,
      "screen": 11,
      "text": 5,
      "typedDataCard": 4
    },
    "DeserializationLoadTime": 3.3880781
  },
  "WasLocalDatabaseReferencesEmpty": true
}