{
  "ComponentIndexes": {},
  "ControlUniqueGuids": {},
  "ControlUniqueIds": {
    "AboutLeaveGallerySeparator": 88,
    "AboutLeaveGallerySeparator_1": 80,
    "AboutLeaveMiddle": 91,
    "AboutLeaveTypeButton": 85,
    "AboutLeaveTypeDescription_1": 303,
    "AboutLeaveTypeGallery": 82,
    "AboutLeaveTypeIcon": 87,
    "AboutLeaveTypeLabel": 86,
    "AboutLeveTypeCell": 84,
    "AboutScreen": 67,
    "AddButton": 130,
    "App": 1,
    "BtnEmployeeLogin": 253,
    "BtnManagerLogin": 256,
    "Button12": 145,
    "Button8_1": 22,
    "Button8_2": 183,
    "ButtonCategories": 203,
    "ButtonCategories_2": 56,
    "ButtonFilter": 201,
    "ButtonFilter2": 54,
    "ButtonManagerApprove_2": 234,
    "ButtonManagerDecline_2": 235,
    "ButtonStatus": 216,
    "ButtonSubmitRequest": 297,
    "CarryForwardDays_2": 224,
    "CDVBHeader": 248,
    "CDVBHeader_1": 100,
    "CDVBHeaderBackground": 240,
    "CDVBHeaderBackground_1": 246,
    "CDVBHeaderBackground_2": 93,
    "CDVBHeaderSubTitle": 243,
    "CDVBHeaderSubTitle_1": 96,
    "CDVBHeaderTitle": 242,
    "CDVBHeaderTitle_1": 95,
    "CDVBHeaderTitle1": 241,
    "CDVBHeaderTitle1_1": 94,
    "CircleHeaderCreateNew_1": 107,
    "CircleHeaderCreateNew_10": 166,
    "CircleHeaderCreateNew_2": 74,
    "CircleHeaderCreateNew_3": 311,
    "CircleHeaderCreateNew_5": 49,
    "CircleHeaderCreateNew_6": 266,
    "CircleHeaderCreateNew_8": 139,
    "CircleHeaderCreateNew_9": 199,
    "CollectionContent": 98,
    "Collections and Variables": 92,
    "CompanyHolidaysScreen": 101,
    "CompanyLogo": 251,
    "Dates": 128,
    "DateTimeSeparator": 291,
    "DeleteIcon": 124,
    "EditIcon_2": 231,
    "EditLable_2": 232,
    "EmployeeLeaveBalance": 133,
    "EmployeeLeaveBalanceGallery": 150,
    "EmployeeLeaveDetail": 160,
    "EmployeeLeaveFilter": 143,
    "ErrorMsg": 127,
    "ExpiryDatePicker": 330,
    "Gallery1_1": 19,
    "Gallery1_2": 180,
    "Gallery2": 5,
    "GalleryHolidays": 120,
    "GalleryNavigation_12": 268,
    "GalleryRequest": 210,
    "galleryTemplate1": 202,
    "galleryTemplate1_2": 144,
    "galleryTemplate1_3": 55,
    "galleryTemplate10": 211,
    "galleryTemplate2": 60,
    "galleryTemplate2_14": 269,
    "galleryTemplate2_8": 276,
    "galleryTemplate2_9": 83,
    "galleryTemplate3_1": 35,
    "galleryTemplate3_2": 151,
    "galleryTemplate4_1": 20,
    "galleryTemplate4_2": 181,
    "galleryTemplate5": 6,
    "galleryTemplate6": 121,
    "galleryTemplate8_1": 319,
    "Group1": 368,
    "Group2": 238,
    "GroupDateSection": 299,
    "GroupLeaveType": 301,
    "GroupNewHoliday": 132,
    "GroupRequestDetails": 237,
    "GroupRequestInfo": 300,
    "Header_1": 298,
    "Header_11": 236,
    "Header_2": 131,
    "Header_3": 90,
    "Header_4": 331,
    "Header_6": 66,
    "Header_7": 159,
    "Header_8": 192,
    "HolidayDate": 129,
    "HolidayDates": 123,
    "HolidayName": 122,
    "HomeScreen": 193,
    "Host": 3,
    "HtmlText1": 245,
    "HtmlText2": 247,
    "HtmlText3": 304,
    "HtmlText3_1": 89,
    "Icon1": 147,
    "Icon2": 322,
    "icon2_1": 265,
    "Icon2_1": 323,
    "icon2_11": 198,
    "icon2_2": 106,
    "icon2_3": 73,
    "icon2_4": 310,
    "icon2_6": 48,
    "icon2_7": 138,
    "icon2_8": 165,
    "Icon3": 316,
    "Icon3_1": 207,
    "Icon4": 170,
    "icon5_10": 97,
    "icon5_9": 244,
    "IconHeaderCreateNew": 200,
    "IconHeaderCreateNew_1": 108,
    "IconHeaderCreateNew_2": 75,
    "IconHeaderCreateNew_3": 312,
    "IconHeaderCreateNew_5": 50,
    "IconHeaderCreateNew_6": 267,
    "IconHeaderCreateNew_8": 140,
    "IconHeaderCreateNew_9": 167,
    "IMPORTANT_NOTE_READ_ME": 239,
    "Label1": 141,
    "Label1_17": 169,
    "Label11": 329,
    "Label11_44": 334,
    "Label11_45": 337,
    "Label11_46": 335,
    "Label11_47": 338,
    "Label11_48": 339,
    "Label11_49": 342,
    "Label11_50": 341,
    "Label11_51": 344,
    "Label11_52": 345,
    "Label11_53": 347,
    "Label11_54": 346,
    "Label11_55": 348,
    "Label11_56": 333,
    "Label11_57": 336,
    "Label11_58": 349,
    "Label11_59": 351,
    "Label11_60": 350,
    "Label11_61": 352,
    "Label11_62": 353,
    "Label11_63": 356,
    "Label11_64": 354,
    "Label11_65": 357,
    "Label11_66": 359,
    "Label11_67": 362,
    "Label11_68": 360,
    "Label11_69": 361,
    "Label11_70": 364,
    "Label11_71": 366,
    "Label11_72": 365,
    "Label11_73": 367,
    "Label11_74": 340,
    "Label11_75": 343,
    "Label15": 315,
    "Label2": 7,
    "Label2_12": 270,
    "Label26": 213,
    "Label28_1": 21,
    "Label28_10": 25,
    "Label28_11": 26,
    "Label28_12": 27,
    "Label28_13": 28,
    "Label28_14": 184,
    "Label28_15": 185,
    "Label28_16": 186,
    "Label28_17": 187,
    "Label28_18": 188,
    "Label28_19": 189,
    "Label28_2": 182,
    "Label28_8": 23,
    "Label28_9": 24,
    "Label29_1": 38,
    "Label29_2": 154,
    "Label3": 214,
    "Label30_1": 41,
    "Label30_2": 157,
    "Label6_1": 325,
    "Label6_2": 324,
    "Label7": 326,
    "Label7_1": 327,
    "Label8": 328,
    "LabelComments": 358,
    "LabelLeaveDetails": 355,
    "LabelRemarks": 363,
    "LabelRemarks_1": 230,
    "LabelRequestLeave": 254,
    "LabelSubmitRequestTo": 295,
    "LblAboutHeader": 71,
    "LblAboutYourLeaveHeader": 293,
    "LblCarryForward_2": 223,
    "LblCurrentLeaveDay": 286,
    "LblCurrentLeaveDayHeader": 285,
    "LblEmployeeLogin": 252,
    "LblErrorMessage": 282,
    "LblFromHeader": 283,
    "LblHeaderCreateNew_1": 105,
    "LblHeaderCreateNew_10": 164,
    "LblHeaderCreateNew_2": 72,
    "LblHeaderCreateNew_3": 309,
    "LblHeaderCreateNew_5": 47,
    "LblHeaderCreateNew_6": 264,
    "LblHeaderCreateNew_8": 137,
    "LblHeaderCreateNew_9": 197,
    "LblHeaderTItle1_1": 261,
    "LblHeaderTItle1_11": 195,
    "LblHeaderTItle1_2": 103,
    "LblHeaderTItle1_3": 69,
    "LblHeaderTItle1_4": 307,
    "LblHeaderTItle1_6": 45,
    "LblHeaderTItle1_7": 135,
    "LblHeaderTItle1_8": 162,
    "LblHeaderTitle2_1": 262,
    "LblHeaderTitle2_11": 196,
    "LblHeaderTitle2_2": 104,
    "LblHeaderTitle2_3": 70,
    "LblHeaderTitle2_4": 308,
    "LblHeaderTitle2_6": 46,
    "LblHeaderTitle2_7": 136,
    "LblHeaderTitle2_8": 163,
    "LblHolidaysHeader": 113,
    "LblInformationHeader": 79,
    "LblInformationHeader2": 81,
    "LblLeaveBalanceLeft": 290,
    "LblLeaveBalanceLeftHeader": 289,
    "LblLeaveDetail": 227,
    "LblLeaveDetailheader": 294,
    "LblLeaveType_2": 219,
    "LblManagerLogin": 255,
    "LblRequestTo_2": 221,
    "LblSelectDatesHeader": 281,
    "LblSubmitRequestHeader": 292,
    "LblToHeader": 284,
    "LblUnpaidLeave_2": 225,
    "Leave_Type_2": 220,
    "LeaveBalanceGallery_1": 34,
    "LeaveBalanceScreen": 305,
    "LeaveDetail": 228,
    "LeaveDetail_txtInput": 296,
    "LeaveEndDatePicker": 288,
    "LeaveStartDatePicker": 287,
    "LeftMenuSeparator_12": 271,
    "LoginAsEmployeeGroup": 257,
    "LoginAsManagerGroup": 258,
    "LoginScreen": 249,
    "MyLeaveBalanceGallery": 318,
    "Navigation": 4,
    "Navigation_1": 51,
    "Navigation_3": 77,
    "Navigation_4": 111,
    "Navigation_5": 204,
    "Navigation_6": 313,
    "Navigation_7": 272,
    "Navigation_8": 142,
    "Navigation_9": 168,
    "NewRequestLeaveTypeGallery": 275,
    "NewRequestScreen": 259,
    "NewRequestSeparator": 280,
    "NextArrow1_1": 39,
    "NextArrow1_2": 155,
    "NRLeaveCellBK": 277,
    "NRLeaveTypeButton": 278,
    "NRLeaveTypeLabel": 279,
    "Rectangle1": 57,
    "Rectangle1_1": 260,
    "Rectangle1_11": 194,
    "Rectangle1_2": 102,
    "Rectangle1_3": 68,
    "Rectangle1_4": 306,
    "Rectangle1_5": 65,
    "Rectangle1_6": 44,
    "Rectangle1_7": 134,
    "Rectangle1_8": 161,
    "Rectangle10_1": 36,
    "Rectangle10_2": 152,
    "Rectangle11_1": 42,
    "Rectangle11_2": 158,
    "Rectangle12": 171,
    "Rectangle12_2": 10,
    "Rectangle12_3": 30,
    "Rectangle12_5": 191,
    "Rectangle13": 8,
    "Rectangle14": 148,
    "Rectangle14_1": 33,
    "Rectangle14_2": 149,
    "Rectangle15_1": 29,
    "Rectangle15_2": 190,
    "Rectangle2": 212,
    "Rectangle2_1": 209,
    "Rectangle3": 250,
    "Rectangle3_2": 110,
    "Rectangle3_3": 76,
    "Rectangle3_4": 206,
    "Rectangle4": 119,
    "Rectangle4_1": 115,
    "Rectangle5": 125,
    "Rectangle6": 317,
    "Rectangle7": 320,
    "Rectangle7_1": 321,
    "Rectangle9": 64,
    "RectNavSep": 205,
    "RectNavSep_1": 112,
    "RectNavSep_2": 78,
    "RectNavSep_3": 314,
    "RectNavSep_5": 52,
    "remarksHeader": 229,
    "RemarksTextBox": 233,
    "Request_To_2": 222,
    "RequestDetailsTitle_2": 208,
    "Screen1": 302,
    "Screen2": 332,
    "Screen3": 9,
    "Screen4": 31,
    "Screen5": 32,
    "SearchLeaveInput": 146,
    "Separator1": 218,
    "SeparatorNavigation": 273,
    "Subtitle1_1": 40,
    "Subtitle1_2": 156,
    "SubtitleEndDate": 217,
    "Title1_1": 37,
    "Title1_2": 153,
    "Title2_10": 12,
    "Title2_11": 13,
    "Title2_12": 14,
    "Title2_13": 15,
    "Title2_14": 16,
    "Title2_15": 17,
    "Title2_16": 18,
    "Title2_17": 172,
    "Title2_18": 173,
    "Title2_19": 174,
    "Title2_20": 175,
    "Title2_21": 176,
    "Title2_22": 177,
    "Title2_23": 178,
    "Title2_24": 179,
    "Title2_9": 11,
    "TitleDates": 117,
    "TitleHeader": 58,
    "TitleHolidayName": 118,
    "TitleNewHoliday": 114,
    "TitleNewRequest": 263,
    "TitlePublicHoliday": 109,
    "TitlePublicHolidays": 116,
    "TitleStartDate": 215,
    "TodayOnLeaveDuration": 63,
    "TodayOnLeaveGallery": 59,
    "TodayOnLeaveName": 61,
    "TodayOnLeaveScreen": 43,
    "TodayOnLeaveTitle": 53,
    "TodayOnLeaveType": 62,
    "txtHoliday": 126,
    "TypeRequestTitle": 274,
    "UnpaidLeave_2": 226,
    "VariablesContent": 99
  },
  "FunctionParamsInvariantScripts": {},
  "FunctionParamsInvariantScriptsOnInstances": {},
  "HeaderLastSavedDateTimeUTC": "12/08/2023 10:01:24",
  "IsLegacyComponentAllowGlobalScopeCase": false,
  "LocalConnectionIDReferences": {
    "12f73af9-777f-4fd4-a512-da2f66fd7501": "\"/providers/microsoft.powerapps/apis/shared_office365/connections/3d056b43935b4a3898e8357d3b3aa727\"",
    "6f72918a-7921-fa64-14bf-78187ad1b172": "\"/providers/microsoft.powerapps/apis/shared_office365users/connections/6042a30c1269401e875bf3ecb2cfc0a6\"",
    "81d384ae-de03-4521-b437-163eeda7a732": "\"/providers/microsoft.powerapps/apis/shared_teams/connections/593bfcc717cb4235bbe2663557dde63c\"",
    "bdef884f-b8ab-424c-8509-321850292346": "\"/providers/microsoft.powerapps/apis/shared_sharepointonline/connections/shared-sharepointonl-2610166f-65d6-4329-9819-5e58e564f198\""
  },
  "LocalDatabaseReferencesAsEmpty": false,
  "LocalResourceFileNames": {
    "Basel_Clock": "0001.svg",
    "Basel_detail_list": "0002.svg",
    "bereavement": "0004.png",
    "bereavement-selected": "0003.png",
    "floating-holiday": "0006.png",
    "floating-holiday-selected": "0005.png",
    "image": "0007.png",
    "Info": "0008.png",
    "jury-duty": "0010.png",
    "jury-duty-selected": "0009.png",
    "login-pic": "0011.png",
    "Logo01": "0012.jpg",
    "RequestLeaveBkg": "0013.png",
    "sick-leave": "0015.png",
    "sick-leave-selected": "0014.png",
    "vacation": "0017.png",
    "vacation-selected": "0016.png"
  },
  "LocalResourceRootPaths": {
    "Basel_Clock": "https://docserverpwaprodseas.blob.core.windows.net/86edddae-0659-4af9-9bb9-42566a9fe9d3-1/resource/Assets0Images00001.svg?skoid=58690ece-ec83-4ce2-9ce8-883d4d6a54ee&sktid=975f013f-7f24-47e8-a7d3-abc4752bf346&skt=2023-12-08T09%3A48%3A50Z&ske=2023-12-09T10%3A03%3A50Z&sks=b&skv=2022-11-02&sv=2022-11-02&spr=https&se=2023-12-09T10%3A03%3A50Z&sr=b&sp=r&sig=dTdRPtjxG7UV7Y9Zx3ThMy8NucxAj3OrFsj6C%2Bi6ZXc%3D",
    "Basel_detail_list": "https://docserverpwaprodseas.blob.core.windows.net/86edddae-0659-4af9-9bb9-42566a9fe9d3-1/resource/Assets0Images00002.svg?skoid=58690ece-ec83-4ce2-9ce8-883d4d6a54ee&sktid=975f013f-7f24-47e8-a7d3-abc4752bf346&skt=2023-12-08T09%3A48%3A50Z&ske=2023-12-09T10%3A03%3A50Z&sks=b&skv=2022-11-02&sv=2022-11-02&spr=https&se=2023-12-09T10%3A03%3A50Z&sr=b&sp=r&sig=VOLwBkqBsjhpg8XEsyJ8iBaYzsb%2FKHBbDbOODCmG6%2BQ%3D",
    "bereavement": "https://docserverpwaprodseas.blob.core.windows.net/86edddae-0659-4af9-9bb9-42566a9fe9d3-1/resource/Assets0Images00004.png?skoid=58690ece-ec83-4ce2-9ce8-883d4d6a54ee&sktid=975f013f-7f24-47e8-a7d3-abc4752bf346&skt=2023-12-08T09%3A48%3A50Z&ske=2023-12-09T10%3A03%3A50Z&sks=b&skv=2022-11-02&sv=2022-11-02&spr=https&se=2023-12-09T10%3A03%3A50Z&sr=b&sp=r&sig=uf8iDBPh35%2B2p%2B2%2B6S%2BkjksMEH3W4WZYq4tXYj5byok%3D",
    "bereavement-selected": "https://docserverpwaprodseas.blob.core.windows.net/86edddae-0659-4af9-9bb9-42566a9fe9d3-1/resource/Assets0Images00003.png?skoid=58690ece-ec83-4ce2-9ce8-883d4d6a54ee&sktid=975f013f-7f24-47e8-a7d3-abc4752bf346&skt=2023-12-08T09%3A48%3A50Z&ske=2023-12-09T10%3A03%3A50Z&sks=b&skv=2022-11-02&sv=2022-11-02&spr=https&se=2023-12-09T10%3A03%3A50Z&sr=b&sp=r&sig=yHU%2By17m8aqyCnM6T%2FWFhcC0VoOhE2vQFUJuh7KS4xs%3D",
    "floating-holiday": "https://docserverpwaprodseas.blob.core.windows.net/86edddae-0659-4af9-9bb9-42566a9fe9d3-1/resource/Assets0Images00006.png?skoid=58690ece-ec83-4ce2-9ce8-883d4d6a54ee&sktid=975f013f-7f24-47e8-a7d3-abc4752bf346&skt=2023-12-08T09%3A48%3A50Z&ske=2023-12-09T10%3A03%3A50Z&sks=b&skv=2022-11-02&sv=2022-11-02&spr=https&se=2023-12-09T10%3A03%3A50Z&sr=b&sp=r&sig=d0xtRnGwjkViF2XgdxwAwL3hD7WpRFrIbjEnDpanIfg%3D",
    "floating-holiday-selected": "https://docserverpwaprodseas.blob.core.windows.net/86edddae-0659-4af9-9bb9-42566a9fe9d3-1/resource/Assets0Images00005.png?skoid=58690ece-ec83-4ce2-9ce8-883d4d6a54ee&sktid=975f013f-7f24-47e8-a7d3-abc4752bf346&skt=2023-12-08T09%3A48%3A50Z&ske=2023-12-09T10%3A03%3A50Z&sks=b&skv=2022-11-02&sv=2022-11-02&spr=https&se=2023-12-09T10%3A03%3A50Z&sr=b&sp=r&sig=8Z0u%2BayuGBTZ%2BqRp6Ff4CkzEj6qn%2BqQ4%2Fr0rUd1xf20%3D",
    "image": "https://docserverpwaprodseas.blob.core.windows.net/86edddae-0659-4af9-9bb9-42566a9fe9d3-1/resource/Assets0Images00007.png?skoid=58690ece-ec83-4ce2-9ce8-883d4d6a54ee&sktid=975f013f-7f24-47e8-a7d3-abc4752bf346&skt=2023-12-08T09%3A48%3A50Z&ske=2023-12-09T10%3A03%3A50Z&sks=b&skv=2022-11-02&sv=2022-11-02&spr=https&se=2023-12-09T10%3A03%3A50Z&sr=b&sp=r&sig=pTf2wYFun0vfGEk1nofsCAzFSJwND3hMgN%2FLHj3etk8%3D",
    "Info": "https://docserverpwaprodseas.blob.core.windows.net/86edddae-0659-4af9-9bb9-42566a9fe9d3-1/resource/Assets0Images00008.png?skoid=58690ece-ec83-4ce2-9ce8-883d4d6a54ee&sktid=975f013f-7f24-47e8-a7d3-abc4752bf346&skt=2023-12-08T09%3A48%3A50Z&ske=2023-12-09T10%3A03%3A50Z&sks=b&skv=2022-11-02&sv=2022-11-02&spr=https&se=2023-12-09T10%3A03%3A50Z&sr=b&sp=r&sig=TyTQg7aRoBdq9%2BUKWwHcoo0%2FXosbfbxE5jy%2BwTqy5uw%3D",
    "jury-duty": "https://docserverpwaprodseas.blob.core.windows.net/86edddae-0659-4af9-9bb9-42566a9fe9d3-1/resource/Assets0Images00010.png?skoid=58690ece-ec83-4ce2-9ce8-883d4d6a54ee&sktid=975f013f-7f24-47e8-a7d3-abc4752bf346&skt=2023-12-08T09%3A48%3A50Z&ske=2023-12-09T10%3A03%3A50Z&sks=b&skv=2022-11-02&sv=2022-11-02&spr=https&se=2023-12-09T10%3A03%3A50Z&sr=b&sp=r&sig=HjhYy0D7y9Y3n%2BsF9RdXhxDURrpYhNMeyLJawgSEvPw%3D",
    "jury-duty-selected": "https://docserverpwaprodseas.blob.core.windows.net/86edddae-0659-4af9-9bb9-42566a9fe9d3-1/resource/Assets0Images00009.png?skoid=58690ece-ec83-4ce2-9ce8-883d4d6a54ee&sktid=975f013f-7f24-47e8-a7d3-abc4752bf346&skt=2023-12-08T09%3A48%3A50Z&ske=2023-12-09T10%3A03%3A50Z&sks=b&skv=2022-11-02&sv=2022-11-02&spr=https&se=2023-12-09T10%3A03%3A50Z&sr=b&sp=r&sig=Px0dwuKGFcwuhqSHwdZZaefSQo9fwUb59RUfCph5w7s%3D",
    "login-pic": "https://docserverpwaprodseas.blob.core.windows.net/86edddae-0659-4af9-9bb9-42566a9fe9d3-1/resource/Assets0Images00011.png?skoid=58690ece-ec83-4ce2-9ce8-883d4d6a54ee&sktid=975f013f-7f24-47e8-a7d3-abc4752bf346&skt=2023-12-08T09%3A48%3A50Z&ske=2023-12-09T10%3A03%3A50Z&sks=b&skv=2022-11-02&sv=2022-11-02&spr=https&se=2023-12-09T10%3A03%3A50Z&sr=b&sp=r&sig=SwAu8UfpHLfTEcp9KBFwUrbNEwcwSHJiVtSRiKimIgI%3D",
    "Logo01": "https://docserverpwaprodseas.blob.core.windows.net/86edddae-0659-4af9-9bb9-42566a9fe9d3-1/resource/Assets0Images00012.jpg?skoid=58690ece-ec83-4ce2-9ce8-883d4d6a54ee&sktid=975f013f-7f24-47e8-a7d3-abc4752bf346&skt=2023-12-08T09%3A48%3A50Z&ske=2023-12-09T10%3A03%3A50Z&sks=b&skv=2022-11-02&sv=2022-11-02&spr=https&se=2023-12-09T10%3A03%3A50Z&sr=b&sp=r&sig=t8QUwt8mv8WYe3LER3fwVplEs5KaLnMm4Qdc9gV05SY%3D",
    "RequestLeaveBkg": "https://docserverpwaprodseas.blob.core.windows.net/86edddae-0659-4af9-9bb9-42566a9fe9d3-1/resource/Assets0Images00013.png?skoid=58690ece-ec83-4ce2-9ce8-883d4d6a54ee&sktid=975f013f-7f24-47e8-a7d3-abc4752bf346&skt=2023-12-08T09%3A48%3A50Z&ske=2023-12-09T10%3A03%3A50Z&sks=b&skv=2022-11-02&sv=2022-11-02&spr=https&se=2023-12-09T10%3A03%3A50Z&sr=b&sp=r&sig=bz05e4X3M09Vv8YsCpHeCQpj8FjyLdtjULond2Ti9%2FA%3D",
    "sick-leave": "https://docserverpwaprodseas.blob.core.windows.net/86edddae-0659-4af9-9bb9-42566a9fe9d3-1/resource/Assets0Images00015.png?skoid=58690ece-ec83-4ce2-9ce8-883d4d6a54ee&sktid=975f013f-7f24-47e8-a7d3-abc4752bf346&skt=2023-12-08T09%3A48%3A50Z&ske=2023-12-09T10%3A03%3A50Z&sks=b&skv=2022-11-02&sv=2022-11-02&spr=https&se=2023-12-09T10%3A03%3A50Z&sr=b&sp=r&sig=zyulAu3cSsJyybDNdfZmPpOyjB6sJ7Uja%2Fq4eVCllSw%3D",
    "sick-leave-selected": "https://docserverpwaprodseas.blob.core.windows.net/86edddae-0659-4af9-9bb9-42566a9fe9d3-1/resource/Assets0Images00014.png?skoid=58690ece-ec83-4ce2-9ce8-883d4d6a54ee&sktid=975f013f-7f24-47e8-a7d3-abc4752bf346&skt=2023-12-08T09%3A48%3A50Z&ske=2023-12-09T10%3A03%3A50Z&sks=b&skv=2022-11-02&sv=2022-11-02&spr=https&se=2023-12-09T10%3A03%3A50Z&sr=b&sp=r&sig=cdBtE4OfTeSqWQarQ4AXAIt94IpzCJSiBw4iAkh%2BRro%3D",
    "vacation": "https://docserverpwaprodseas.blob.core.windows.net/86edddae-0659-4af9-9bb9-42566a9fe9d3-1/resource/Assets0Images00017.png?skoid=58690ece-ec83-4ce2-9ce8-883d4d6a54ee&sktid=975f013f-7f24-47e8-a7d3-abc4752bf346&skt=2023-12-08T09%3A48%3A50Z&ske=2023-12-09T10%3A03%3A50Z&sks=b&skv=2022-11-02&sv=2022-11-02&spr=https&se=2023-12-09T10%3A03%3A50Z&sr=b&sp=r&sig=ZpjorXkriJrfl%2Bbd%2FxODgdIsr68iblDNzx44SC5qS4U%3D",
    "vacation-selected": "https://docserverpwaprodseas.blob.core.windows.net/86edddae-0659-4af9-9bb9-42566a9fe9d3-1/resource/Assets0Images00016.png?skoid=58690ece-ec83-4ce2-9ce8-883d4d6a54ee&sktid=975f013f-7f24-47e8-a7d3-abc4752bf346&skt=2023-12-08T09%3A48%3A50Z&ske=2023-12-09T10%3A03%3A50Z&sks=b&skv=2022-11-02&sv=2022-11-02&spr=https&se=2023-12-09T10%3A03%3A50Z&sr=b&sp=r&sig=H%2FZeDJKvD0LwG4L9w9Xx1purDDbgPvtDqEUaJAG4BjY%3D"
  },
  "OldLogoFileName": "logo.jpg",
  "OrderComponentMetadata": {
    "b6b5e691fc474668b7b6312386d8a5c2": 0
  },
  "OrderComponentTemplate": {
    "b6b5e691fc474668b7b6312386d8a5c2": 0
  },
  "OrderDataSource": {
    "_OnLeaveFilter": 19,
    "ComboBoxSample": 4,
    "CustomGallerySample": 5,
    "DropDownSample": 6,
    "EmailTemplate": 14,
    "EmployeeNavigation": 15,
    "HolidayCollection": 16,
    "LeaveApp_Employee": 7,
    "LeaveApp_Employee_Entitlement": 8,
    "LeaveApp_Entitlement": 9,
    "LeaveApp_HR/Admin": 10,
    "LeaveApp_PublicHoliday": 11,
    "LeaveApp_Request": 12,
    "LeaveTypeCollection": 17,
    "ListboxSample": 13,
    "ManagerNavigation": 18,
    "MicrosoftTeams": 0,
    "Office365": 1,
    "Office365Users": 2,
    "Office365Users_1": 3
  },
  "OrderGroupControls": {
    "AboutLeaveMiddle": {
      "AboutLeaveGallerySeparator": 2,
      "AboutLeaveTypeGallery": 1,
      "HtmlText3_1": 3,
      "LblInformationHeader2": 0
    },
    "CDVBHeader": {
      "CDVBHeaderBackground": 0,
      "CDVBHeaderSubTitle": 1,
      "CDVBHeaderTitle": 2,
      "CDVBHeaderTitle1": 3
    },
    "CDVBHeader_1": {
      "CDVBHeaderBackground_2": 0,
      "CDVBHeaderSubTitle_1": 1,
      "CDVBHeaderTitle_1": 2,
      "CDVBHeaderTitle1_1": 3
    },
    "Group1": {
      "LabelComments": 2,
      "LabelLeaveDetails": 1,
      "LabelRemarks": 0
    },
    "Group2": {
      "ButtonManagerApprove_2": 4,
      "ButtonManagerDecline_2": 5,
      "CarryForwardDays_2": 8,
      "EditIcon_2": 3,
      "EditLable_2": 2,
      "LabelRemarks_1": 16,
      "LblCarryForward_2": 12,
      "LblLeaveType_2": 10,
      "LblRequestTo_2": 11,
      "LblUnpaidLeave_2": 13,
      "Leave_Type_2": 6,
      "Rectangle3_4": 0,
      "remarksHeader": 15,
      "RemarksTextBox": 14,
      "Request_To_2": 7,
      "RequestDetailsTitle_2": 1,
      "UnpaidLeave_2": 9
    },
    "GroupDateSection": {
      "LblCurrentLeaveDay": 8,
      "LblCurrentLeaveDayHeader": 7,
      "LblErrorMessage": 9,
      "LblFromHeader": 2,
      "LblLeaveBalanceLeft": 6,
      "LblLeaveBalanceLeftHeader": 5,
      "LblSelectDatesHeader": 0,
      "LblToHeader": 1,
      "LeaveEndDatePicker": 4,
      "LeaveStartDatePicker": 3
    },
    "GroupLeaveType": {
      "NewRequestLeaveTypeGallery": 0,
      "NewRequestSeparator": 2,
      "TypeRequestTitle": 1
    },
    "GroupNewHoliday": {
      "AddButton": 6,
      "Dates": 5,
      "ErrorMsg": 7,
      "HolidayDate": 3,
      "Rectangle3_2": 0,
      "TitleHolidayName": 4,
      "TitleNewHoliday": 1,
      "txtHoliday": 2
    },
    "GroupRequestDetails": {},
    "GroupRequestInfo": {
      "DateTimeSeparator": 4,
      "LblAboutYourLeaveHeader": 1,
      "LblLeaveDetailheader": 2,
      "LblSubmitRequestHeader": 0,
      "LeaveDetail_txtInput": 3
    },
    "Header_1": {
      "CircleHeaderCreateNew_6": 4,
      "icon2_1": 3,
      "IconHeaderCreateNew_6": 5,
      "LblHeaderCreateNew_6": 6,
      "LblHeaderTItle1_1": 1,
      "LblHeaderTitle2_1": 2,
      "Rectangle1_1": 0
    },
    "Header_11": {
      "CircleHeaderCreateNew_9": 4,
      "icon2_11": 3,
      "IconHeaderCreateNew": 5,
      "LblHeaderCreateNew_9": 6,
      "LblHeaderTItle1_11": 1,
      "LblHeaderTitle2_11": 2,
      "Rectangle1_11": 0
    },
    "Header_2": {
      "CircleHeaderCreateNew_1": 4,
      "icon2_2": 3,
      "IconHeaderCreateNew_1": 5,
      "LblHeaderCreateNew_1": 6,
      "LblHeaderTItle1_2": 1,
      "LblHeaderTitle2_2": 2,
      "Rectangle1_2": 0
    },
    "Header_3": {
      "CircleHeaderCreateNew_2": 4,
      "icon2_3": 3,
      "IconHeaderCreateNew_2": 5,
      "LblHeaderCreateNew_2": 6,
      "LblHeaderTItle1_3": 1,
      "LblHeaderTitle2_3": 2,
      "Rectangle1_3": 0
    },
    "Header_4": {
      "CircleHeaderCreateNew_3": 4,
      "icon2_4": 3,
      "IconHeaderCreateNew_3": 5,
      "LblHeaderCreateNew_3": 6,
      "LblHeaderTItle1_4": 1,
      "LblHeaderTitle2_4": 2,
      "Rectangle1_4": 0
    },
    "Header_6": {
      "CircleHeaderCreateNew_5": 4,
      "icon2_6": 3,
      "IconHeaderCreateNew_5": 5,
      "LblHeaderCreateNew_5": 6,
      "LblHeaderTItle1_6": 1,
      "LblHeaderTitle2_6": 2,
      "Rectangle1_6": 0
    },
    "Header_7": {
      "CircleHeaderCreateNew_8": 4,
      "icon2_7": 3,
      "IconHeaderCreateNew_8": 5,
      "LblHeaderCreateNew_8": 6,
      "LblHeaderTItle1_7": 1,
      "LblHeaderTitle2_7": 2,
      "Rectangle1_7": 0
    },
    "Header_8": {
      "CircleHeaderCreateNew_10": 4,
      "icon2_8": 3,
      "IconHeaderCreateNew_9": 5,
      "LblHeaderCreateNew_10": 6,
      "LblHeaderTItle1_8": 1,
      "LblHeaderTitle2_8": 2,
      "Rectangle1_8": 0
    },
    "LoginAsEmployeeGroup": {
      "BtnEmployeeLogin": 1,
      "LblEmployeeLogin": 0
    },
    "LoginAsManagerGroup": {
      "BtnManagerLogin": 1,
      "LblManagerLogin": 0
    }
  },
  "OrderPcfTemplate": {},
  "OrderTemplate": {},
  "OrderXMLTemplate": {
    "button": 3,
    "circle": 5,
    "datepicker": 9,
    "gallery": 2,
    "htmlViewer": 7,
    "icon": 4,
    "image": 6,
    "label": 1,
    "rectangle": 0,
    "text": 8
  },
  "OverridablePropertiesEntry": {
    "AboutLeaveGallerySeparator": {},
    "AboutLeaveGallerySeparator_1": {},
    "AboutLeaveMiddle": {},
    "AboutLeaveTypeButton": {},
    "AboutLeaveTypeDescription_1": {},
    "AboutLeaveTypeGallery": {},
    "AboutLeaveTypeIcon": {},
    "AboutLeaveTypeLabel": {},
    "AboutLeveTypeCell": {},
    "AboutScreen": {},
    "AddButton": {},
    "App": {},
    "BtnEmployeeLogin": {},
    "BtnManagerLogin": {},
    "Button12": {},
    "Button8_1": {},
    "Button8_2": {},
    "ButtonCategories": {},
    "ButtonCategories_2": {},
    "ButtonFilter": {},
    "ButtonFilter2": {},
    "ButtonManagerApprove_2": {},
    "ButtonManagerDecline_2": {},
    "ButtonStatus": {},
    "ButtonSubmitRequest": {},
    "CarryForwardDays_2": {},
    "CDVBHeader": {},
    "CDVBHeader_1": {},
    "CDVBHeaderBackground": {},
    "CDVBHeaderBackground_1": {},
    "CDVBHeaderBackground_2": {},
    "CDVBHeaderSubTitle": {},
    "CDVBHeaderSubTitle_1": {},
    "CDVBHeaderTitle": {},
    "CDVBHeaderTitle_1": {},
    "CDVBHeaderTitle1": {},
    "CDVBHeaderTitle1_1": {},
    "CircleHeaderCreateNew_1": {},
    "CircleHeaderCreateNew_10": {},
    "CircleHeaderCreateNew_2": {},
    "CircleHeaderCreateNew_3": {},
    "CircleHeaderCreateNew_5": {},
    "CircleHeaderCreateNew_6": {},
    "CircleHeaderCreateNew_8": {},
    "CircleHeaderCreateNew_9": {},
    "CollectionContent": {},
    "Collections and Variables": {},
    "CompanyHolidaysScreen": {},
    "CompanyLogo": {},
    "Dates": {},
    "DateTimeSeparator": {},
    "DeleteIcon": {},
    "EditIcon_2": {},
    "EditLable_2": {},
    "EmployeeLeaveBalance": {},
    "EmployeeLeaveBalanceGallery": {},
    "EmployeeLeaveDetail": {},
    "EmployeeLeaveFilter": {},
    "ErrorMsg": {},
    "ExpiryDatePicker": {},
    "Gallery1_1": {},
    "Gallery1_2": {},
    "Gallery2": {},
    "GalleryHolidays": {},
    "GalleryNavigation_12": {},
    "GalleryRequest": {},
    "galleryTemplate1": {},
    "galleryTemplate1_2": {},
    "galleryTemplate1_3": {},
    "galleryTemplate10": {},
    "galleryTemplate2": {},
    "galleryTemplate2_14": {},
    "galleryTemplate2_8": {},
    "galleryTemplate2_9": {},
    "galleryTemplate3_1": {},
    "galleryTemplate3_2": {},
    "galleryTemplate4_1": {},
    "galleryTemplate4_2": {},
    "galleryTemplate5": {},
    "galleryTemplate6": {},
    "galleryTemplate8_1": {},
    "Group1": {},
    "Group2": {},
    "GroupDateSection": {},
    "GroupLeaveType": {},
    "GroupNewHoliday": {},
    "GroupRequestDetails": {},
    "GroupRequestInfo": {},
    "Header_1": {},
    "Header_11": {},
    "Header_2": {},
    "Header_3": {},
    "Header_4": {},
    "Header_6": {},
    "Header_7": {},
    "Header_8": {},
    "HolidayDate": {},
    "HolidayDates": {},
    "HolidayName": {},
    "HomeScreen": {},
    "Host": {},
    "HtmlText1": {},
    "HtmlText2": {},
    "HtmlText3": {},
    "HtmlText3_1": {},
    "Icon1": {},
    "Icon2": {},
    "icon2_1": {},
    "Icon2_1": {},
    "icon2_11": {},
    "icon2_2": {},
    "icon2_3": {},
    "icon2_4": {},
    "icon2_6": {},
    "icon2_7": {},
    "icon2_8": {},
    "Icon3": {},
    "Icon3_1": {},
    "Icon4": {},
    "icon5_10": {},
    "icon5_9": {},
    "IconHeaderCreateNew": {},
    "IconHeaderCreateNew_1": {},
    "IconHeaderCreateNew_2": {},
    "IconHeaderCreateNew_3": {},
    "IconHeaderCreateNew_5": {},
    "IconHeaderCreateNew_6": {},
    "IconHeaderCreateNew_8": {},
    "IconHeaderCreateNew_9": {},
    "IMPORTANT_NOTE_READ_ME": {},
    "Label1": {},
    "Label1_17": {},
    "Label11": {},
    "Label11_44": {},
    "Label11_45": {},
    "Label11_46": {},
    "Label11_47": {},
    "Label11_48": {},
    "Label11_49": {},
    "Label11_50": {},
    "Label11_51": {},
    "Label11_52": {},
    "Label11_53": {},
    "Label11_54": {},
    "Label11_55": {},
    "Label11_56": {},
    "Label11_57": {},
    "Label11_58": {},
    "Label11_59": {},
    "Label11_60": {},
    "Label11_61": {},
    "Label11_62": {},
    "Label11_63": {},
    "Label11_64": {},
    "Label11_65": {},
    "Label11_66": {},
    "Label11_67": {},
    "Label11_68": {},
    "Label11_69": {},
    "Label11_70": {},
    "Label11_71": {},
    "Label11_72": {},
    "Label11_73": {},
    "Label11_74": {},
    "Label11_75": {},
    "Label15": {},
    "Label2": {},
    "Label2_12": {},
    "Label26": {},
    "Label28_1": {},
    "Label28_10": {},
    "Label28_11": {},
    "Label28_12": {},
    "Label28_13": {},
    "Label28_14": {},
    "Label28_15": {},
    "Label28_16": {},
    "Label28_17": {},
    "Label28_18": {},
    "Label28_19": {},
    "Label28_2": {},
    "Label28_8": {},
    "Label28_9": {},
    "Label29_1": {},
    "Label29_2": {},
    "Label3": {},
    "Label30_1": {},
    "Label30_2": {},
    "Label6_1": {},
    "Label6_2": {},
    "Label7": {},
    "Label7_1": {},
    "Label8": {},
    "LabelComments": {},
    "LabelLeaveDetails": {},
    "LabelRemarks": {},
    "LabelRemarks_1": {},
    "LabelRequestLeave": {},
    "LabelSubmitRequestTo": {},
    "LblAboutHeader": {},
    "LblAboutYourLeaveHeader": {},
    "LblCarryForward_2": {},
    "LblCurrentLeaveDay": {},
    "LblCurrentLeaveDayHeader": {},
    "LblEmployeeLogin": {},
    "LblErrorMessage": {},
    "LblFromHeader": {},
    "LblHeaderCreateNew_1": {},
    "LblHeaderCreateNew_10": {},
    "LblHeaderCreateNew_2": {},
    "LblHeaderCreateNew_3": {},
    "LblHeaderCreateNew_5": {},
    "LblHeaderCreateNew_6": {},
    "LblHeaderCreateNew_8": {},
    "LblHeaderCreateNew_9": {},
    "LblHeaderTItle1_1": {},
    "LblHeaderTItle1_11": {},
    "LblHeaderTItle1_2": {},
    "LblHeaderTItle1_3": {},
    "LblHeaderTItle1_4": {},
    "LblHeaderTItle1_6": {},
    "LblHeaderTItle1_7": {},
    "LblHeaderTItle1_8": {},
    "LblHeaderTitle2_1": {},
    "LblHeaderTitle2_11": {},
    "LblHeaderTitle2_2": {},
    "LblHeaderTitle2_3": {},
    "LblHeaderTitle2_4": {},
    "LblHeaderTitle2_6": {},
    "LblHeaderTitle2_7": {},
    "LblHeaderTitle2_8": {},
    "LblHolidaysHeader": {},
    "LblInformationHeader": {},
    "LblInformationHeader2": {},
    "LblLeaveBalanceLeft": {},
    "LblLeaveBalanceLeftHeader": {},
    "LblLeaveDetail": {},
    "LblLeaveDetailheader": {},
    "LblLeaveType_2": {},
    "LblManagerLogin": {},
    "LblRequestTo_2": {},
    "LblSelectDatesHeader": {},
    "LblSubmitRequestHeader": {},
    "LblToHeader": {},
    "LblUnpaidLeave_2": {},
    "Leave_Type_2": {},
    "LeaveBalanceGallery_1": {},
    "LeaveBalanceScreen": {},
    "LeaveDetail": {},
    "LeaveDetail_txtInput": {},
    "LeaveEndDatePicker": {},
    "LeaveStartDatePicker": {},
    "LeftMenuSeparator_12": {},
    "LoginAsEmployeeGroup": {},
    "LoginAsManagerGroup": {},
    "LoginScreen": {},
    "MyLeaveBalanceGallery": {},
    "Navigation": {},
    "Navigation_1": {},
    "Navigation_3": {},
    "Navigation_4": {},
    "Navigation_5": {},
    "Navigation_6": {},
    "Navigation_7": {},
    "Navigation_8": {},
    "Navigation_9": {},
    "NewRequestLeaveTypeGallery": {},
    "NewRequestScreen": {},
    "NewRequestSeparator": {},
    "NextArrow1_1": {},
    "NextArrow1_2": {},
    "NRLeaveCellBK": {},
    "NRLeaveTypeButton": {},
    "NRLeaveTypeLabel": {},
    "Rectangle1": {},
    "Rectangle1_1": {},
    "Rectangle1_11": {},
    "Rectangle1_2": {},
    "Rectangle1_3": {},
    "Rectangle1_4": {},
    "Rectangle1_5": {},
    "Rectangle1_6": {},
    "Rectangle1_7": {},
    "Rectangle1_8": {},
    "Rectangle10_1": {},
    "Rectangle10_2": {},
    "Rectangle11_1": {},
    "Rectangle11_2": {},
    "Rectangle12": {},
    "Rectangle12_2": {},
    "Rectangle12_3": {},
    "Rectangle12_5": {},
    "Rectangle13": {},
    "Rectangle14": {},
    "Rectangle14_1": {},
    "Rectangle14_2": {},
    "Rectangle15_1": {},
    "Rectangle15_2": {},
    "Rectangle2": {},
    "Rectangle2_1": {},
    "Rectangle3": {},
    "Rectangle3_2": {},
    "Rectangle3_3": {},
    "Rectangle3_4": {},
    "Rectangle4": {},
    "Rectangle4_1": {},
    "Rectangle5": {},
    "Rectangle6": {},
    "Rectangle7": {},
    "Rectangle7_1": {},
    "Rectangle9": {},
    "RectNavSep": {},
    "RectNavSep_1": {},
    "RectNavSep_2": {},
    "RectNavSep_3": {},
    "RectNavSep_5": {},
    "remarksHeader": {},
    "RemarksTextBox": {},
    "Request_To_2": {},
    "RequestDetailsTitle_2": {},
    "Screen1": {},
    "Screen2": {},
    "Screen3": {},
    "Screen4": {},
    "Screen5": {},
    "SearchLeaveInput": {},
    "Separator1": {},
    "SeparatorNavigation": {},
    "Subtitle1_1": {},
    "Subtitle1_2": {},
    "SubtitleEndDate": {},
    "Title1_1": {},
    "Title1_2": {},
    "Title2_10": {},
    "Title2_11": {},
    "Title2_12": {},
    "Title2_13": {},
    "Title2_14": {},
    "Title2_15": {},
    "Title2_16": {},
    "Title2_17": {},
    "Title2_18": {},
    "Title2_19": {},
    "Title2_20": {},
    "Title2_21": {},
    "Title2_22": {},
    "Title2_23": {},
    "Title2_24": {},
    "Title2_9": {},
    "TitleDates": {},
    "TitleHeader": {},
    "TitleHolidayName": {},
    "TitleNewHoliday": {},
    "TitleNewRequest": {},
    "TitlePublicHoliday": {},
    "TitlePublicHolidays": {},
    "TitleStartDate": {},
    "TodayOnLeaveDuration": {},
    "TodayOnLeaveGallery": {},
    "TodayOnLeaveName": {},
    "TodayOnLeaveScreen": {},
    "TodayOnLeaveTitle": {},
    "TodayOnLeaveType": {},
    "txtHoliday": {},
    "TypeRequestTitle": {},
    "UnpaidLeave_2": {},
    "VariablesContent": {}
  },
  "PCFDynamicSchemaForIRRetrievalEntry": {},
  "PCFTemplateEntry": {},
  "PublishOrderIndices": {
    "AboutLeaveGallerySeparator": 181,
    "AboutLeaveGallerySeparator_1": 172,
    "AboutLeaveMiddle": 173,
    "AboutLeaveTypeButton": 178,
    "AboutLeaveTypeDescription_1": 342,
    "AboutLeaveTypeGallery": 175,
    "AboutLeaveTypeIcon": 180,
    "AboutLeaveTypeLabel": 179,
    "AboutLeveTypeCell": 177,
    "AboutScreen": 6,
    "AddButton": 158,
    "App": 0,
    "BtnEmployeeLogin": 4,
    "BtnManagerLogin": 8,
    "Button12": 229,
    "Button8_1": 323,
    "Button8_2": 266,
    "ButtonCategories": 29,
    "ButtonCategories_2": 76,
    "ButtonFilter": 27,
    "ButtonFilter2": 74,
    "ButtonManagerApprove_2": 61,
    "ButtonManagerDecline_2": 62,
    "ButtonStatus": 43,
    "ButtonSubmitRequest": 127,
    "CarryForwardDays_2": 51,
    "CDVBHeader": 14,
    "CDVBHeader_1": 214,
    "CDVBHeaderBackground": 9,
    "CDVBHeaderBackground_1": 16,
    "CDVBHeaderBackground_2": 209,
    "CDVBHeaderSubTitle": 12,
    "CDVBHeaderSubTitle_1": 212,
    "CDVBHeaderTitle": 11,
    "CDVBHeaderTitle_1": 211,
    "CDVBHeaderTitle1": 10,
    "CDVBHeaderTitle1_1": 210,
    "CircleHeaderCreateNew_1": 134,
    "CircleHeaderCreateNew_10": 248,
    "CircleHeaderCreateNew_2": 166,
    "CircleHeaderCreateNew_3": 189,
    "CircleHeaderCreateNew_5": 69,
    "CircleHeaderCreateNew_6": 92,
    "CircleHeaderCreateNew_8": 223,
    "CircleHeaderCreateNew_9": 24,
    "CollectionContent": 215,
    "Collections and Variables": 33,
    "CompanyHolidaysScreen": 42,
    "CompanyLogo": 1,
    "Dates": 156,
    "DateTimeSeparator": 121,
    "DeleteIcon": 152,
    "EditIcon_2": 58,
    "EditLable_2": 59,
    "EmployeeLeaveBalance": 74,
    "EmployeeLeaveBalanceGallery": 234,
    "EmployeeLeaveDetail": 101,
    "EmployeeLeaveFilter": 227,
    "ErrorMsg": 155,
    "ExpiryDatePicker": 208,
    "Gallery1_1": 320,
    "Gallery1_2": 263,
    "Gallery2": 344,
    "GalleryHolidays": 148,
    "GalleryNavigation_12": 98,
    "GalleryRequest": 37,
    "galleryTemplate1": 28,
    "galleryTemplate1_2": 228,
    "galleryTemplate1_3": 75,
    "galleryTemplate10": 38,
    "galleryTemplate2": 80,
    "galleryTemplate2_14": 99,
    "galleryTemplate2_8": 106,
    "galleryTemplate2_9": 176,
    "galleryTemplate3_1": 334,
    "galleryTemplate3_2": 235,
    "galleryTemplate4_1": 321,
    "galleryTemplate4_2": 264,
    "galleryTemplate5": 345,
    "galleryTemplate6": 149,
    "galleryTemplate8_1": 197,
    "Group1": 275,
    "Group2": 33,
    "GroupDateSection": 95,
    "GroupLeaveType": 97,
    "GroupNewHoliday": 137,
    "GroupRequestDetails": 26,
    "GroupRequestInfo": 96,
    "Header_1": 94,
    "Header_11": 19,
    "Header_2": 129,
    "Header_3": 160,
    "Header_4": 184,
    "Header_6": 64,
    "Header_7": 218,
    "Header_8": 250,
    "HolidayDate": 157,
    "HolidayDates": 151,
    "HolidayName": 150,
    "HomeScreen": 134,
    "Host": 0,
    "HtmlText1": 15,
    "HtmlText2": 17,
    "HtmlText3": 343,
    "HtmlText3_1": 182,
    "Icon1": 231,
    "Icon2": 200,
    "icon2_1": 91,
    "Icon2_1": 201,
    "icon2_11": 23,
    "icon2_2": 133,
    "icon2_3": 165,
    "icon2_4": 188,
    "icon2_6": 68,
    "icon2_7": 222,
    "icon2_8": 247,
    "Icon3": 194,
    "Icon3_1": 34,
    "Icon4": 253,
    "icon5_10": 213,
    "icon5_9": 13,
    "IconHeaderCreateNew": 25,
    "IconHeaderCreateNew_1": 135,
    "IconHeaderCreateNew_2": 167,
    "IconHeaderCreateNew_3": 190,
    "IconHeaderCreateNew_5": 70,
    "IconHeaderCreateNew_6": 93,
    "IconHeaderCreateNew_8": 224,
    "IconHeaderCreateNew_9": 249,
    "IMPORTANT_NOTE_READ_ME": 180,
    "Label1": 225,
    "Label1_17": 252,
    "Label11": 207,
    "Label11_44": 277,
    "Label11_45": 280,
    "Label11_46": 278,
    "Label11_47": 281,
    "Label11_48": 282,
    "Label11_49": 285,
    "Label11_50": 284,
    "Label11_51": 287,
    "Label11_52": 288,
    "Label11_53": 290,
    "Label11_54": 289,
    "Label11_55": 291,
    "Label11_56": 276,
    "Label11_57": 279,
    "Label11_58": 292,
    "Label11_59": 294,
    "Label11_60": 293,
    "Label11_61": 295,
    "Label11_62": 296,
    "Label11_63": 299,
    "Label11_64": 297,
    "Label11_65": 300,
    "Label11_66": 302,
    "Label11_67": 305,
    "Label11_68": 303,
    "Label11_69": 304,
    "Label11_70": 307,
    "Label11_71": 309,
    "Label11_72": 308,
    "Label11_73": 310,
    "Label11_74": 283,
    "Label11_75": 286,
    "Label15": 193,
    "Label2": 346,
    "Label2_12": 100,
    "Label26": 40,
    "Label28_1": 322,
    "Label28_10": 326,
    "Label28_11": 327,
    "Label28_12": 328,
    "Label28_13": 329,
    "Label28_14": 267,
    "Label28_15": 268,
    "Label28_16": 269,
    "Label28_17": 270,
    "Label28_18": 271,
    "Label28_19": 272,
    "Label28_2": 265,
    "Label28_8": 324,
    "Label28_9": 325,
    "Label29_1": 337,
    "Label29_2": 238,
    "Label3": 41,
    "Label30_1": 340,
    "Label30_2": 241,
    "Label6_1": 203,
    "Label6_2": 202,
    "Label7": 204,
    "Label7_1": 205,
    "Label8": 206,
    "LabelComments": 301,
    "LabelLeaveDetails": 298,
    "LabelRemarks": 306,
    "LabelRemarks_1": 57,
    "LabelRequestLeave": 5,
    "LabelSubmitRequestTo": 125,
    "LblAboutHeader": 163,
    "LblAboutYourLeaveHeader": 123,
    "LblCarryForward_2": 50,
    "LblCurrentLeaveDay": 116,
    "LblCurrentLeaveDayHeader": 115,
    "LblEmployeeLogin": 3,
    "LblErrorMessage": 112,
    "LblFromHeader": 113,
    "LblHeaderCreateNew_1": 132,
    "LblHeaderCreateNew_10": 246,
    "LblHeaderCreateNew_2": 164,
    "LblHeaderCreateNew_3": 187,
    "LblHeaderCreateNew_5": 67,
    "LblHeaderCreateNew_6": 90,
    "LblHeaderCreateNew_8": 221,
    "LblHeaderCreateNew_9": 22,
    "LblHeaderTItle1_1": 88,
    "LblHeaderTItle1_11": 20,
    "LblHeaderTItle1_2": 130,
    "LblHeaderTItle1_3": 161,
    "LblHeaderTItle1_4": 185,
    "LblHeaderTItle1_6": 65,
    "LblHeaderTItle1_7": 219,
    "LblHeaderTItle1_8": 244,
    "LblHeaderTitle2_1": 89,
    "LblHeaderTitle2_11": 21,
    "LblHeaderTitle2_2": 131,
    "LblHeaderTitle2_3": 162,
    "LblHeaderTitle2_4": 186,
    "LblHeaderTitle2_6": 66,
    "LblHeaderTitle2_7": 220,
    "LblHeaderTitle2_8": 245,
    "LblHolidaysHeader": 141,
    "LblInformationHeader": 171,
    "LblInformationHeader2": 174,
    "LblLeaveBalanceLeft": 120,
    "LblLeaveBalanceLeftHeader": 119,
    "LblLeaveDetail": 54,
    "LblLeaveDetailheader": 124,
    "LblLeaveType_2": 46,
    "LblManagerLogin": 6,
    "LblRequestTo_2": 48,
    "LblSelectDatesHeader": 111,
    "LblSubmitRequestHeader": 122,
    "LblToHeader": 114,
    "LblUnpaidLeave_2": 52,
    "Leave_Type_2": 47,
    "LeaveBalanceGallery_1": 333,
    "LeaveBalanceScreen": 190,
    "LeaveDetail": 55,
    "LeaveDetail_txtInput": 126,
    "LeaveEndDatePicker": 118,
    "LeaveStartDatePicker": 117,
    "LeftMenuSeparator_12": 101,
    "LoginAsEmployeeGroup": 2,
    "LoginAsManagerGroup": 7,
    "LoginScreen": 217,
    "MyLeaveBalanceGallery": 196,
    "Navigation": 1,
    "Navigation_1": 71,
    "Navigation_3": 169,
    "Navigation_4": 139,
    "Navigation_5": 30,
    "Navigation_6": 191,
    "Navigation_7": 102,
    "Navigation_8": 226,
    "Navigation_9": 251,
    "NewRequestLeaveTypeGallery": 105,
    "NewRequestScreen": 227,
    "NewRequestSeparator": 110,
    "NextArrow1_1": 338,
    "NextArrow1_2": 239,
    "NRLeaveCellBK": 107,
    "NRLeaveTypeButton": 108,
    "NRLeaveTypeLabel": 109,
    "Rectangle1": 77,
    "Rectangle1_1": 86,
    "Rectangle1_11": 18,
    "Rectangle1_2": 128,
    "Rectangle1_3": 159,
    "Rectangle1_4": 183,
    "Rectangle1_5": 85,
    "Rectangle1_6": 63,
    "Rectangle1_7": 217,
    "Rectangle1_8": 243,
    "Rectangle10_1": 335,
    "Rectangle10_2": 236,
    "Rectangle11_1": 341,
    "Rectangle11_2": 242,
    "Rectangle12": 254,
    "Rectangle12_2": 311,
    "Rectangle12_3": 331,
    "Rectangle12_5": 274,
    "Rectangle13": 347,
    "Rectangle14": 232,
    "Rectangle14_1": 332,
    "Rectangle14_2": 233,
    "Rectangle15_1": 330,
    "Rectangle15_2": 273,
    "Rectangle2": 39,
    "Rectangle2_1": 36,
    "Rectangle3": 0,
    "Rectangle3_2": 138,
    "Rectangle3_3": 168,
    "Rectangle3_4": 32,
    "Rectangle4": 147,
    "Rectangle4_1": 143,
    "Rectangle5": 153,
    "Rectangle6": 195,
    "Rectangle7": 198,
    "Rectangle7_1": 199,
    "Rectangle9": 84,
    "RectNavSep": 31,
    "RectNavSep_1": 140,
    "RectNavSep_2": 170,
    "RectNavSep_3": 192,
    "RectNavSep_5": 72,
    "remarksHeader": 56,
    "RemarksTextBox": 60,
    "Request_To_2": 49,
    "RequestDetailsTitle_2": 35,
    "Screen1": 270,
    "Screen2": 273,
    "Screen3": 310,
    "Screen4": 332,
    "Screen5": 333,
    "SearchLeaveInput": 230,
    "Separator1": 45,
    "SeparatorNavigation": 103,
    "Subtitle1_1": 339,
    "Subtitle1_2": 240,
    "SubtitleEndDate": 44,
    "Title1_1": 336,
    "Title1_2": 237,
    "Title2_10": 313,
    "Title2_11": 314,
    "Title2_12": 315,
    "Title2_13": 316,
    "Title2_14": 317,
    "Title2_15": 318,
    "Title2_16": 319,
    "Title2_17": 255,
    "Title2_18": 256,
    "Title2_19": 257,
    "Title2_20": 258,
    "Title2_21": 259,
    "Title2_22": 260,
    "Title2_23": 261,
    "Title2_24": 262,
    "Title2_9": 312,
    "TitleDates": 145,
    "TitleHeader": 78,
    "TitleHolidayName": 146,
    "TitleNewHoliday": 142,
    "TitleNewRequest": 87,
    "TitlePublicHoliday": 136,
    "TitlePublicHolidays": 144,
    "TitleStartDate": 42,
    "TodayOnLeaveDuration": 83,
    "TodayOnLeaveGallery": 79,
    "TodayOnLeaveName": 81,
    "TodayOnLeaveScreen": 344,
    "TodayOnLeaveTitle": 73,
    "TodayOnLeaveType": 82,
    "txtHoliday": 154,
    "TypeRequestTitle": 104,
    "UnpaidLeave_2": 53,
    "VariablesContent": 216
  },
  "ResourcesJsonIndices": {
    "Image-Basel_Add": 0,
    "Image-Basel_ArrowRight": 1,
    "Image-Basel_ArrowsUpDown": 2,
    "Image-Basel_Cancel": 3,
    "Image-Basel_Check": 4,
    "Image-Basel_ChevronLeft": 5,
    "Image-Basel_ChevronRight": 6,
    "Image-Basel_Clock": 15,
    "Image-Basel_detail_list": 16,
    "Image-Basel_Edit": 7,
    "Image-Basel_Hamburger": 8,
    "Image-Basel_Information": 9,
    "Image-Basel_Mail": 10,
    "Image-Basel_Person": 11,
    "Image-Basel_Reload": 12,
    "Image-Basel_Search": 13,
    "Image-bereavement": 18,
    "Image-bereavement-selected": 17,
    "Image-floating-holiday": 20,
    "Image-floating-holiday-selected": 19,
    "Image-image": 21,
    "Image-Info": 22,
    "Image-jury-duty": 24,
    "Image-jury-duty-selected": 23,
    "Image-login-pic": 25,
    "Image-Logo01": 26,
    "Image-RequestLeaveBkg": 27,
    "Image-SampleImage": 14,
    "Image-sick-leave": 29,
    "Image-sick-leave-selected": 28,
    "Image-vacation": 31,
    "Image-vacation-selected": 30
  },
  "RuleScreenIdWithoutScreen": {},
  "TemplateVersions": {},
  "VolatileProperties": {
    "AnalysisLoadTime": 2.1284438,
    "ControlCount": {
      "b6b5e691fc474668b7b6312386d8a5c2": 9,
      "button": 14,
      "circle": 8,
      "datepicker": 4,
      "gallery": 15,
      "galleryTemplate": 15,
      "group": 20,
      "htmlViewer": 6,
      "icon": 28,
      "image": 2,
      "label": 170,
      "rectangle": 54,
      "screen": 16,
      "text": 4
    },
    "DeserializationLoadTime": 3.9664152
  },
  "WasLocalDatabaseReferencesEmpty": true
}